{
  "authorDailyContributionsMap": {
    "raivatshah": [
      {
        "insertions": 4878,
        "deletions": 4240,
        "date": "2020-03-17",
        "commitResults": [
          {
            "hash": "c9d5d255e4b11133064233f30f352992c8d986a5",
            "messageTitle": "add Group Class",
            "messageBody": "",
            "insertions": 70,
            "deletions": 0
          },
          {
            "hash": "e71699eca3e47553dfa5edcaaadc009ea9375f3d",
            "messageTitle": "add Hashcode to Group class",
            "messageBody": "",
            "insertions": 6,
            "deletions": 0
          },
          {
            "hash": "9f417d710bd6be0a7bae38921cc314f8e0b9dd83",
            "messageTitle": "change command word for add to add_person",
            "messageBody": "",
            "insertions": 1,
            "deletions": 1
          },
          {
            "hash": "4a849af34fbf011b1c2ef085dadfe75dc04a1ef4",
            "messageTitle": "add file: AddGroupCommand.java",
            "messageBody": "",
            "insertions": 49,
            "deletions": 0
          },
          {
            "hash": "a6726cf24d2a58cb93658810de0f03a59e00714d",
            "messageTitle": "add command to AddressBook parser",
            "messageBody": "",
            "insertions": 24,
            "deletions": 20
          },
          {
            "hash": "7d5b36c91e36251787a7e10fa3755ee7c7c4fed4",
            "messageTitle": "Add AddGroupCommandParser",
            "messageBody": "",
            "insertions": 48,
            "deletions": 0
          },
          {
            "hash": "91b85bd392e2fea59960de736dfccbae1660e129",
            "messageTitle": "Create UniqueGroupList",
            "messageBody": "",
            "insertions": 46,
            "deletions": 1
          },
          {
            "hash": "c6bcc45f4f2f80cb86c7a16d530d006c0aed120c",
            "messageTitle": "fix bugs so that add_group command works",
            "messageBody": "",
            "insertions": 21,
            "deletions": 1
          },
          {
            "hash": "4d406824079ab3e1fc341a2ccba2d555c441cc8e",
            "messageTitle": "add print method to group class",
            "messageBody": "",
            "insertions": 20,
            "deletions": 0
          },
          {
            "hash": "9a1dca425cbd46d67a8fc9180cac2ebfb5590fb4",
            "messageTitle": "fix all checkstyle issues",
            "messageBody": "",
            "insertions": 4593,
            "deletions": 4217
          }
        ]
      },
      {
        "insertions": 3571,
        "deletions": 3432,
        "date": "2020-03-18",
        "commitResults": [
          {
            "hash": "b37cfe3c7850be59f6d1ed5872f65ca07481a480",
            "messageTitle": "fix checkstyle issues",
            "messageBody": "",
            "insertions": 3,
            "deletions": 3
          },
          {
            "hash": "cb3904960a112661ffd31b7dbb79c7e226dac279",
            "messageTitle": "fix addCommandTest",
            "messageBody": "",
            "insertions": 11,
            "deletions": 1
          },
          {
            "hash": "812e21ad6aa2f6cecfdfb740bb4f630de77ad53c",
            "messageTitle": "fix checkstyle issues in /test",
            "messageBody": "",
            "insertions": 3557,
            "deletions": 3428
          }
        ]
      },
      {
        "insertions": 83,
        "deletions": 2,
        "date": "2020-03-22",
        "commitResults": [
          {
            "hash": "001acd2c2339e9b1e7e7849182a930e1b0aa76cb",
            "messageTitle": "Add time class and JUnit tests for it",
            "messageBody": "",
            "insertions": 81,
            "deletions": 0
          },
          {
            "hash": "3d866c4454c567c84c528ed4bfa657cfa66dc54e",
            "messageTitle": "fix TimeTest error",
            "messageBody": "",
            "insertions": 1,
            "deletions": 1
          },
          {
            "hash": "245ab1cfda96fde62a4103ff5f55795bfc12fd34",
            "messageTitle": "change ListCommand Message to list_persons from list",
            "messageBody": "",
            "insertions": 1,
            "deletions": 1
          }
        ]
      },
      {
        "insertions": 388,
        "deletions": 78,
        "date": "2020-03-23",
        "commitResults": [
          {
            "hash": "d7aab4b07cb50dc1fb8975d5bb3e0e83950c0748",
            "messageTitle": "setup logic of list_groups command",
            "messageBody": "",
            "insertions": 126,
            "deletions": 28
          },
          {
            "hash": "666d3afb472eb61531003f9fafa00ea193f513e4",
            "messageTitle": "setup UI for list_groups",
            "messageBody": "",
            "insertions": 160,
            "deletions": 7
          },
          {
            "hash": "29dce6f22a4a2b6ae57dc59466c906d21390df19",
            "messageTitle": "modify Group Class structure",
            "messageBody": "",
            "insertions": 22,
            "deletions": 29
          },
          {
            "hash": "4a81c61e7a66f6084937dc55048a9b4af8fb3178",
            "messageTitle": "add test for Group",
            "messageBody": "",
            "insertions": 58,
            "deletions": 11
          },
          {
            "hash": "f8a8a1e489961e4d773a7ee3114a96bbb108d665",
            "messageTitle": "fix checkstyle issue for GroupPanelList.fxml",
            "messageBody": "",
            "insertions": 1,
            "deletions": 1
          },
          {
            "hash": "9b711c798cd697b70f51a30c5245208783517170",
            "messageTitle": "add test for hasGroup in ModelManagerTest.java",
            "messageBody": "",
            "insertions": 12,
            "deletions": 0
          },
          {
            "hash": "25badc27c3553540c2652a4152d8e80e9cee0099",
            "messageTitle": "add test case in AddressBookParserTest.java",
            "messageBody": "",
            "insertions": 7,
            "deletions": 0
          },
          {
            "hash": "1f37976f11a25574cf430fe02623f576f56e25b2",
            "messageTitle": "remove faulty testcase",
            "messageBody": "",
            "insertions": 2,
            "deletions": 2
          }
        ]
      },
      {
        "insertions": 203,
        "deletions": 6,
        "date": "2020-03-24",
        "commitResults": [
          {
            "hash": "54fe9b51a1cde966dad420bd9759040659ccd85b",
            "messageTitle": "change command word for DeleteCommand to delete_person instead of delete",
            "messageBody": "",
            "insertions": 1,
            "deletions": 1
          },
          {
            "hash": "ae807e53224844ab0b8675318a1691c9144f04cf",
            "messageTitle": "create DeleteGroupCommand class",
            "messageBody": "",
            "insertions": 66,
            "deletions": 0
          },
          {
            "hash": "36eebab779ab42d4dbcc7543bd6e5a4eebe29982",
            "messageTitle": "fix error message for groupinvalid index",
            "messageBody": "",
            "insertions": 37,
            "deletions": 2
          },
          {
            "hash": "0b8d92d235158be516b51d024e327dea86a04b8b",
            "messageTitle": "add test cases for delete_group",
            "messageBody": "",
            "insertions": 32,
            "deletions": 1
          },
          {
            "hash": "b069ab4def334751314dbb7a718056145073dfb0",
            "messageTitle": "add test case for hasGroup",
            "messageBody": "",
            "insertions": 7,
            "deletions": 0
          },
          {
            "hash": "bd68981182bc27e590baac7a7b9321c48ce532ee",
            "messageTitle": "add more test cases to AddresBookTest.java",
            "messageBody": "",
            "insertions": 11,
            "deletions": 0
          },
          {
            "hash": "676e95352afa13eeafc98a49cc3ba503bfbb7c43",
            "messageTitle": "add test for parseCommand delete_group",
            "messageBody": "",
            "insertions": 7,
            "deletions": 0
          },
          {
            "hash": "e154c64714f196dbc53d860f9775908887afc8b8",
            "messageTitle": "add test case for removeGroup() method",
            "messageBody": "",
            "insertions": 22,
            "deletions": 2
          },
          {
            "hash": "1b50c58791dd83ed1d5afb3125ed52306a87604e",
            "messageTitle": "add test case for AddressBook Method",
            "messageBody": "",
            "insertions": 6,
            "deletions": 0
          },
          {
            "hash": "4e525e78bb777b5ff369bf8fb70833a3c40f5aa8",
            "messageTitle": "add new testcase for hasGroup",
            "messageBody": "",
            "insertions": 8,
            "deletions": 0
          },
          {
            "hash": "699edaeb786609f6340f197e993723a5d60ea5c6",
            "messageTitle": "add test case for ListGroup command",
            "messageBody": "",
            "insertions": 6,
            "deletions": 0
          }
        ]
      }
    ],
    "terencemah": [
      {
        "insertions": 447,
        "deletions": 84,
        "date": "2020-03-17",
        "commitResults": [
          {
            "hash": "bd8936cffbdaa45c5a39db2982efd2974789cf1f",
            "messageTitle": "Add View Command (incomplete)",
            "messageBody": "",
            "insertions": 192,
            "deletions": 0
          },
          {
            "hash": "daa612f90ea16f676895d44e8a17f2cd1898361c",
            "messageTitle": "Add View Command functionality",
            "messageBody": "",
            "insertions": 242,
            "deletions": 80
          },
          {
            "hash": "6fb0031f500aa088a6e4f6275ba907346f4e2a80",
            "messageTitle": "Fix issue with FrequencyListPanel controller",
            "messageBody": "",
            "insertions": 1,
            "deletions": 2
          },
          {
            "hash": "a1a026079020e200d673a6a8747f518baa9a68b7",
            "messageTitle": "Fix some Checkstyle issues",
            "messageBody": "",
            "insertions": 12,
            "deletions": 2
          }
        ]
      },
      {
        "insertions": 43,
        "deletions": 3,
        "date": "2020-03-18",
        "commitResults": [
          {
            "hash": "9846eb5c655c501a2b8bd22a2150e487c2573872",
            "messageTitle": "Fix Checkstyle issues",
            "messageBody": "",
            "insertions": 43,
            "deletions": 3
          }
        ]
      },
      {
        "insertions": 2,
        "deletions": 2,
        "date": "2020-03-24",
        "commitResults": [
          {
            "hash": "d480cef10a92fd733dcc8d9f0a0e823ce726b995",
            "messageTitle": "Update Developer Guide",
            "messageBody": "",
            "insertions": 2,
            "deletions": 2
          }
        ]
      },
      {
        "insertions": 1,
        "deletions": 2,
        "date": "2020-03-25",
        "commitResults": [
          {
            "hash": "12e4df97446d3a86c20f5d150302ed38545f2b08",
            "messageTitle": "Fix checkstyle issue?",
            "messageBody": "",
            "insertions": 1,
            "deletions": 2
          }
        ]
      }
    ],
    "harrychengly": [
      {
        "insertions": 2,
        "deletions": 2,
        "date": "2020-02-18",
        "commitResults": [
          {
            "hash": "0860a502a1060bf19c0bd221ec5bfab070fa4102",
            "messageTitle": "testing Travis CI",
            "messageBody": "",
            "insertions": 1,
            "deletions": 1
          },
          {
            "hash": "a7a3a0b5b46cf4d4e72f8d5ff186817f8a9bbc69",
            "messageTitle": "testing Travis CI 2",
            "messageBody": "",
            "insertions": 1,
            "deletions": 1
          }
        ]
      },
      {
        "insertions": 2,
        "deletions": 2,
        "date": "2020-03-03",
        "commitResults": [
          {
            "hash": "573321fa132211665fd4409e6bfe94aef69de946",
            "messageTitle": "Updated readme, about us, contact us page (#9)",
            "messageBody": "* Updated readme, about us, contact us page\r\n\r\n* fixed checkstyle",
            "insertions": 2,
            "deletions": 2
          }
        ]
      },
      {
        "insertions": 366,
        "deletions": 30,
        "date": "2020-03-16",
        "commitResults": [
          {
            "hash": "0b47d8dd04e62962423a9fc2bbdcfa85ead8c419",
            "messageTitle": "import csv feature",
            "messageBody": "",
            "insertions": 259,
            "deletions": 8
          },
          {
            "hash": "9cf94204af1052bac434f058ca4d82311129ac96",
            "messageTitle": "pass checkstyleTest",
            "messageBody": "",
            "insertions": 11,
            "deletions": 0
          },
          {
            "hash": "2d111fedc756db7d8396abdc1f25b81cb2cfd9b1",
            "messageTitle": "Fixed jackson data-formmat-csv version error",
            "messageBody": "",
            "insertions": 4,
            "deletions": 4
          },
          {
            "hash": "535632004ab2e62fd2cfe52253087788829b77a5",
            "messageTitle": "improving coveralls",
            "messageBody": "",
            "insertions": 39,
            "deletions": 1
          },
          {
            "hash": "c6be4b1ba1958a0fc7ece4790852d098f82be737",
            "messageTitle": "passed checkstyleTest",
            "messageBody": "",
            "insertions": 14,
            "deletions": 14
          },
          {
            "hash": "fea63fa7d7b9bd037919274c35b9cbd7467a0bad",
            "messageTitle": "added test cases",
            "messageBody": "",
            "insertions": 39,
            "deletions": 2
          },
          {
            "hash": "aac8ddbbb125842e32f96712792b11d8dc7601ab",
            "messageTitle": "fixed checkstyle",
            "messageBody": "",
            "insertions": 0,
            "deletions": 1
          }
        ]
      },
      {
        "insertions": 215,
        "deletions": 16,
        "date": "2020-03-17",
        "commitResults": [
          {
            "hash": "9e21dd66948983baebc7036518d27299a3024d7e",
            "messageTitle": "added new test cases",
            "messageBody": "",
            "insertions": 53,
            "deletions": 0
          },
          {
            "hash": "1be215cb29e230dae136804d9612a90f434785ed",
            "messageTitle": "export command",
            "messageBody": "",
            "insertions": 156,
            "deletions": 10
          },
          {
            "hash": "bcfe8ed8c216b5ab792bfa60719052643effcc69",
            "messageTitle": "fixed checkstyle",
            "messageBody": "",
            "insertions": 6,
            "deletions": 6
          }
        ]
      },
      {
        "insertions": 7,
        "deletions": 7,
        "date": "2020-03-21",
        "commitResults": [
          {
            "hash": "c0c6eed269021232462b69ffbb8ea53900796ed9",
            "messageTitle": " added new colors",
            "messageBody": "",
            "insertions": 7,
            "deletions": 7
          }
        ]
      },
      {
        "insertions": 2,
        "deletions": 2,
        "date": "2020-03-26",
        "commitResults": [
          {
            "hash": "d7cdf16414f672634a79b7a9549c769eaf999d27",
            "messageTitle": "Minor updates to DG",
            "messageBody": "",
            "insertions": 2,
            "deletions": 2
          }
        ]
      }
    ],
    "l2ejected": [
      {
        "insertions": 93,
        "deletions": 0,
        "date": "2020-03-10",
        "commitResults": [
          {
            "hash": "481ce0c48b294d2d0f72d8c568632b634e344e63",
            "messageTitle": "interim event class added to seedu.address.model",
            "messageBody": "",
            "insertions": 93,
            "deletions": 0
          }
        ]
      },
      {
        "insertions": 305,
        "deletions": 162,
        "date": "2020-03-17",
        "commitResults": [
          {
            "hash": "f7c9c54a8eecd558de47883d1e0f8b4dad68ae4c",
            "messageTitle": "init random command",
            "messageBody": "",
            "insertions": 4,
            "deletions": 0
          },
          {
            "hash": "50fd7d7651d2926160bce4ebabfdd507d6d38f8a",
            "messageTitle": "init random command",
            "messageBody": "",
            "insertions": 37,
            "deletions": 3
          },
          {
            "hash": "0c5752b6ac3cbebc51c3e592a4e916e8a1d697a3",
            "messageTitle": "time functionality added",
            "messageBody": "",
            "insertions": 264,
            "deletions": 159
          }
        ]
      },
      {
        "insertions": 292,
        "deletions": 524,
        "date": "2020-03-18",
        "commitResults": [
          {
            "hash": "b9de1735e2bde1c517a14bfa290d6b2410a5d8a6",
            "messageTitle": "fixed errors causing Travis to fail",
            "messageBody": "",
            "insertions": 7,
            "deletions": 15
          },
          {
            "hash": "4006c00fec7da762ada6e57e5b3355a83409ee0f",
            "messageTitle": "removed unused import statement",
            "messageBody": "",
            "insertions": 1,
            "deletions": 1
          },
          {
            "hash": "695f6205fa34ab3765f1936f9c686636b13bd632",
            "messageTitle": "interim fixes and test cases for time",
            "messageBody": "",
            "insertions": 12,
            "deletions": 0
          },
          {
            "hash": "7965b794015448d964dc89060c94fbe80f1b25e5",
            "messageTitle": "fixes for time command",
            "messageBody": "",
            "insertions": 237,
            "deletions": 36
          },
          {
            "hash": "1a43723e1fd4877245f41d76194580c7d815d858",
            "messageTitle": "removed Time",
            "messageBody": "",
            "insertions": 23,
            "deletions": 457
          },
          {
            "hash": "1f6fc29676b2f2879bcc2335429f39b30e6ba8f7",
            "messageTitle": "more deletes of time usages",
            "messageBody": "",
            "insertions": 11,
            "deletions": 14
          },
          {
            "hash": "0821f2a4c27420bf60b47e047f1ca0af7aaf805d",
            "messageTitle": "more editing",
            "messageBody": "",
            "insertions": 1,
            "deletions": 1
          }
        ]
      },
      {
        "insertions": 884,
        "deletions": 316,
        "date": "2020-03-23",
        "commitResults": [
          {
            "hash": "d2309bf77ca86b712dcb43d01ffff26541a80ad6",
            "messageTitle": "Add event and functionalities added",
            "messageBody": "",
            "insertions": 420,
            "deletions": 3
          },
          {
            "hash": "9e385c5c35869a604d27baec39da880c74855f91",
            "messageTitle": "resolving merge conflict",
            "messageBody": "",
            "insertions": 1,
            "deletions": 1
          },
          {
            "hash": "1225c636b8602b34b0948909d94f9b4a11127eda",
            "messageTitle": "checkstyle fixes for test files",
            "messageBody": "",
            "insertions": 19,
            "deletions": 25
          },
          {
            "hash": "6c6dc4b40c01fae802f4af9a384e39e64b42ceec",
            "messageTitle": "fixed spelling mistake",
            "messageBody": "",
            "insertions": 1,
            "deletions": 1
          },
          {
            "hash": "9279cdff32b1eebf9650f8b85751782ec066d653",
            "messageTitle": "fixed failing testcases",
            "messageBody": "",
            "insertions": 7,
            "deletions": 7
          },
          {
            "hash": "0a47f9dfd782c3652c9a9d7bf895298f55a54d7e",
            "messageTitle": "fixed failing testcases",
            "messageBody": "",
            "insertions": 2,
            "deletions": 2
          },
          {
            "hash": "10db6fe0de835dcfef1fb5d9a8b5e4c55405681f",
            "messageTitle": "fixes for failing test cases",
            "messageBody": "",
            "insertions": 1,
            "deletions": 7
          },
          {
            "hash": "845fb763f973bfbdbb357b888d8366496c8164b0",
            "messageTitle": "fixed failing test cases",
            "messageBody": "",
            "insertions": 130,
            "deletions": 34
          },
          {
            "hash": "cc7cf44aa35b838de3f21be7f62efe72c92e782b",
            "messageTitle": "fixed failing test case",
            "messageBody": "",
            "insertions": 4,
            "deletions": 2
          },
          {
            "hash": "98996b3972c07b38cf83d5956ed5b2c4ff2215a2",
            "messageTitle": "removed failing test case",
            "messageBody": "",
            "insertions": 16,
            "deletions": 24
          },
          {
            "hash": "35b9ec28379456edc809309de0cfd6276d770196",
            "messageTitle": "removed trouble shooting edits",
            "messageBody": "",
            "insertions": 16,
            "deletions": 16
          },
          {
            "hash": "c724e0c2775c332be96ea7b7be03f12a6144d40f",
            "messageTitle": "deleted empty files",
            "messageBody": "",
            "insertions": 0,
            "deletions": 0
          },
          {
            "hash": "9e3eef1e26955931f21b97d610f954a61837327e",
            "messageTitle": "fixed time not saving",
            "messageBody": "",
            "insertions": 4,
            "deletions": 0
          },
          {
            "hash": "3749b21c846e4312e8bcae12d7ad4400956a6aaa",
            "messageTitle": "fixed time not saving",
            "messageBody": "",
            "insertions": 262,
            "deletions": 117
          },
          {
            "hash": "6977ec29579e7c22f6d9ae414399ed20e0ecd6ef",
            "messageTitle": "shifted Time class to person package",
            "messageBody": "",
            "insertions": 1,
            "deletions": 77
          }
        ]
      },
      {
        "insertions": 236,
        "deletions": 84,
        "date": "2020-03-24",
        "commitResults": [
          {
            "hash": "1e82cd3c9f262e3496b378236f8e686a3dc12138",
            "messageTitle": "more test case added",
            "messageBody": "",
            "insertions": 25,
            "deletions": 1
          },
          {
            "hash": "8aca8d65e85724d2dc5d6183d910263843c171d0",
            "messageTitle": "more test cases added",
            "messageBody": "",
            "insertions": 58,
            "deletions": 13
          },
          {
            "hash": "86a9698feba5386f029db1f9af3e42d9986f8eab",
            "messageTitle": "more test cases added \u0026 checkstye fix",
            "messageBody": "",
            "insertions": 45,
            "deletions": 26
          },
          {
            "hash": "0f45270181a0800a2649e0c5d66751b0d9ea3d5d",
            "messageTitle": "minor edits",
            "messageBody": "",
            "insertions": 2,
            "deletions": 2
          },
          {
            "hash": "eef49ef902d392324bc1eb84e25a212a6c306eee",
            "messageTitle": "more test cases added",
            "messageBody": "",
            "insertions": 86,
            "deletions": 38
          },
          {
            "hash": "972359f531c9d98c83d21f8aa1784a8a957a0041",
            "messageTitle": "more test cases",
            "messageBody": "",
            "insertions": 8,
            "deletions": 0
          },
          {
            "hash": "cba2bc647e6c3ec4df7bc27a3f5b072e7a1bcc63",
            "messageTitle": "more test cases",
            "messageBody": "",
            "insertions": 8,
            "deletions": 0
          },
          {
            "hash": "92fb2addf4df8623220d5fc42f20f578452662b5",
            "messageTitle": "add more test case",
            "messageBody": "",
            "insertions": 4,
            "deletions": 0
          },
          {
            "hash": "77c732727cb66ea78413bf757bd5a2ca4759c9e8",
            "messageTitle": "removed redundant test case",
            "messageBody": "",
            "insertions": 0,
            "deletions": 4
          }
        ]
      },
      {
        "insertions": 19,
        "deletions": 12,
        "date": "2020-03-25",
        "commitResults": [
          {
            "hash": "2307330bfa66f5314320c9e91806956dc9f1694c",
            "messageTitle": "DG updates",
            "messageBody": "",
            "insertions": 17,
            "deletions": 11
          },
          {
            "hash": "184c2724e76d935f799173f4b1c1ab4e17250bf8",
            "messageTitle": "DG changes",
            "messageBody": "",
            "insertions": 2,
            "deletions": 1
          }
        ]
      }
    ]
  },
  "authorFinalContributionMap": {
    "raivatshah": 1970,
    "terencemah": 451,
    "harrychengly": 523,
    "l2ejected": 825
  },
  "authorFileTypeContributionMap": {
    "raivatshah": {
      "java": 1931,
      "md": 0,
      "fxml": 39,
      "sh": 0,
      "bat": 0,
      "gradle": 0,
      "txt": 0
    },
    "terencemah": {
      "java": 435,
      "md": 0,
      "fxml": 16,
      "sh": 0,
      "bat": 0,
      "gradle": 0,
      "txt": 0
    },
    "harrychengly": {
      "java": 510,
      "md": 0,
      "fxml": 9,
      "sh": 0,
      "bat": 0,
      "gradle": 4,
      "txt": 0
    },
    "l2ejected": {
      "java": 823,
      "md": 0,
      "fxml": 1,
      "sh": 0,
      "bat": 0,
      "gradle": 1,
      "txt": 0
    }
  },
  "authorContributionVariance": {
    "raivatshah": 2991976.8,
    "terencemah": 6570.9897,
    "harrychengly": 4768.2964,
    "l2ejected": 53142.168
  },
  "authorDisplayNameMap": {
    "raivatshah": "CS2103-W14-4 RAIV..SHAH",
    "terencemah": "CS2103-W14-4 MAH ..ENCE",
    "harrychengly": "CS2103-W14-4 CHEN.. YAW",
    "l2ejected": "CS2103-W14-4 ERNE..QUAN"
  }
}
