{
  "authorDailyContributionsMap": {
    "sancharib-git": [
      {
        "insertions": 584,
        "deletions": 277,
        "date": "2020-03-02",
        "commitResults": [
          {
            "hash": "d208799795e7218ea9b087a822cf7526a90a472f",
            "messageTitle": "tutorial removing field",
            "messageBody": "",
            "insertions": 81,
            "deletions": 202
          },
          {
            "hash": "2bca562f95ae0af1a2ff4480e69adb221a6f1415",
            "messageTitle": "tutorial adding command",
            "messageBody": "",
            "insertions": 503,
            "deletions": 75
          }
        ]
      },
      {
        "insertions": 4,
        "deletions": 3,
        "date": "2020-03-03",
        "commitResults": [
          {
            "hash": "0f3642dcfd18e6cb2b8bcb166fb7a053b3a4f669",
            "messageTitle": "added newline:",
            "messageBody": "",
            "insertions": 4,
            "deletions": 3
          }
        ]
      },
      {
        "insertions": 150,
        "deletions": 232,
        "date": "2020-03-05",
        "commitResults": [
          {
            "hash": "883cc919c78b377b616997723b64994cf411c8a8",
            "messageTitle": "fixed checkstyle",
            "messageBody": "",
            "insertions": 13,
            "deletions": 29
          },
          {
            "hash": "d3e54a6ddc270596beb512f32d1e10622cf3fbcc",
            "messageTitle": "fixed checkstyle",
            "messageBody": "",
            "insertions": 1,
            "deletions": 1
          },
          {
            "hash": "bbf0146b033c1a95e654b1e35a5cfee0ec8f0fa9",
            "messageTitle": "fixed checkstyle",
            "messageBody": "",
            "insertions": 1,
            "deletions": 1
          },
          {
            "hash": "c6c921355e27d9a5809cac2801531cd811386d23",
            "messageTitle": "fixed checkstyle",
            "messageBody": "",
            "insertions": 2,
            "deletions": 2
          },
          {
            "hash": "913780996d1856666ae76ab770f3e35175a81e4a",
            "messageTitle": "fixed compile errors",
            "messageBody": "",
            "insertions": 16,
            "deletions": 40
          },
          {
            "hash": "4e2955ac1d9894792758fb2a28d878ba12203960",
            "messageTitle": "fixed test checkstyle errors",
            "messageBody": "",
            "insertions": 68,
            "deletions": 137
          },
          {
            "hash": "22b34673b5495c5d5a5b3a54ef0d7c39bfa853dd",
            "messageTitle": "fixed main checkstyle errors",
            "messageBody": "",
            "insertions": 3,
            "deletions": 0
          },
          {
            "hash": "53271e4f57e6d33ffb6b54e4c5e041cb66d3b49c",
            "messageTitle": "fixed main checkstyle errors",
            "messageBody": "",
            "insertions": 2,
            "deletions": 1
          },
          {
            "hash": "8c5cf702c70ff0e420520eeb37d07646580aab11",
            "messageTitle": "fixed test checkstyle errors",
            "messageBody": "",
            "insertions": 33,
            "deletions": 7
          },
          {
            "hash": "c214b6d40f432ea6b5b8171108b068e633c6f53a",
            "messageTitle": "fixed test checkstyle errors",
            "messageBody": "",
            "insertions": 8,
            "deletions": 4
          },
          {
            "hash": "67377e1b2ced7900ffad3953bb6650c1d0c7fc46",
            "messageTitle": "fixed test checkstyle errors",
            "messageBody": "",
            "insertions": 3,
            "deletions": 2
          },
          {
            "hash": "00efa0b80a67c52b84f82679b16a989159aa3efe",
            "messageTitle": "fixed test errors",
            "messageBody": "",
            "insertions": 0,
            "deletions": 8
          }
        ]
      },
      {
        "insertions": 334,
        "deletions": 105,
        "date": "2020-03-16",
        "commitResults": [
          {
            "hash": "7a97d397b173280deb3fc7c2f826ef6052fede83",
            "messageTitle": "reserve command",
            "messageBody": "",
            "insertions": 274,
            "deletions": 12
          },
          {
            "hash": "3a4cf1b9539af8be3345a631d638729594c87833",
            "messageTitle": "checkstyle",
            "messageBody": "",
            "insertions": 56,
            "deletions": 84
          },
          {
            "hash": "389a900a7726adc179ec9fa2b911fd46683b3d71",
            "messageTitle": "compile issue",
            "messageBody": "",
            "insertions": 0,
            "deletions": 3
          },
          {
            "hash": "51a96af97e215263538d15bca3472f3b6ed0d9be",
            "messageTitle": "checkstyle",
            "messageBody": "",
            "insertions": 4,
            "deletions": 6
          }
        ]
      },
      {
        "insertions": 266,
        "deletions": 113,
        "date": "2020-03-17",
        "commitResults": [
          {
            "hash": "79e65f481f9ca505c67cf57d8acec2a0b3e6e800",
            "messageTitle": "added tests for reserve",
            "messageBody": "",
            "insertions": 152,
            "deletions": 2
          },
          {
            "hash": "6f927eccd54bf3f1375fb025bd926d82f5813eea",
            "messageTitle": "minor changes",
            "messageBody": "",
            "insertions": 3,
            "deletions": 15
          },
          {
            "hash": "f013c8d284b48fe960cde87e4f319d04d5a62e9c",
            "messageTitle": " fixed compile issues",
            "messageBody": "",
            "insertions": 14,
            "deletions": 15
          },
          {
            "hash": "d4f4f2f2bda6099eb612306a8b0dcc2838b94f6c",
            "messageTitle": "fixed checkstyle",
            "messageBody": "",
            "insertions": 1,
            "deletions": 1
          },
          {
            "hash": "cbb54165566cdea4397aa69a0b5be72b89cc1c2c",
            "messageTitle": "fixed checkstyle",
            "messageBody": "",
            "insertions": 19,
            "deletions": 16
          },
          {
            "hash": "7ed6fc5109250739ff7f3faf478324ceb97a4c5f",
            "messageTitle": "test issues",
            "messageBody": "",
            "insertions": 4,
            "deletions": 4
          },
          {
            "hash": "cc34cfb36d5d5fc610a95fb3c5cadb197fa4b065",
            "messageTitle": "removed unecessary field",
            "messageBody": "",
            "insertions": 0,
            "deletions": 4
          },
          {
            "hash": "6110a9d9e4d1fb3409f2330d00979b3404d424a8",
            "messageTitle": "changed comment",
            "messageBody": "",
            "insertions": 1,
            "deletions": 1
          },
          {
            "hash": "81014f8dac0e4d5a655898d87c634fc2693036d3",
            "messageTitle": "test issues",
            "messageBody": "",
            "insertions": 12,
            "deletions": 6
          },
          {
            "hash": "888476dd37f5ef25d9aa95df24029a26ad5b031a",
            "messageTitle": "test issue",
            "messageBody": "",
            "insertions": 7,
            "deletions": 2
          },
          {
            "hash": "cd6e51d0b787a0993cb77d5c7219c573f7b08551",
            "messageTitle": "checkstyle",
            "messageBody": "",
            "insertions": 2,
            "deletions": 2
          },
          {
            "hash": "9469961d37448639baa73034ec4cbd602fb442cd",
            "messageTitle": "test",
            "messageBody": "",
            "insertions": 3,
            "deletions": 3
          },
          {
            "hash": "143731a2d4ada1615d63613ecb272529d28d62f3",
            "messageTitle": "fixed test issues",
            "messageBody": "",
            "insertions": 41,
            "deletions": 36
          },
          {
            "hash": "55a8c790466acd52311bb84410fd201f915d2019",
            "messageTitle": "checkstyle",
            "messageBody": "",
            "insertions": 5,
            "deletions": 5
          },
          {
            "hash": "45bdb6c5410cd4333760d2867dc82e704cd04ac9",
            "messageTitle": "checkstyle",
            "messageBody": "",
            "insertions": 2,
            "deletions": 1
          }
        ]
      },
      {
        "insertions": 147,
        "deletions": 8,
        "date": "2020-03-20",
        "commitResults": [
          {
            "hash": "d332f1c07f4e6bb2178c01b15855a6c1dc1e6eaf",
            "messageTitle": "merge",
            "messageBody": "",
            "insertions": 0,
            "deletions": 2
          },
          {
            "hash": "c15de884aee9d31cd7fd6a44cb6209ed36340a7e",
            "messageTitle": "viewroomlist",
            "messageBody": "",
            "insertions": 147,
            "deletions": 6
          }
        ]
      },
      {
        "insertions": 816,
        "deletions": 114,
        "date": "2020-03-24",
        "commitResults": [
          {
            "hash": "0133c024e3ccbcc3d71edcf251796d4685fb1772",
            "messageTitle": "tied storage to addroom command and model",
            "messageBody": "",
            "insertions": 619,
            "deletions": 65
          },
          {
            "hash": "6cb790875c949c62907b005d9a6591d4107467b6",
            "messageTitle": "able to view rooms in main window",
            "messageBody": "",
            "insertions": 56,
            "deletions": 22
          },
          {
            "hash": "5732c0fb884d7567dce7147d6fcedd654a3324b8",
            "messageTitle": "fixed errors",
            "messageBody": "",
            "insertions": 125,
            "deletions": 16
          },
          {
            "hash": "a480fb5a1df95f6d64685c98ad9141bea961387f",
            "messageTitle": "fix conflict",
            "messageBody": "",
            "insertions": 1,
            "deletions": 1
          },
          {
            "hash": "9830640aabd7529814e4c428fc0a0c4ef0b3da54",
            "messageTitle": "fixed issues",
            "messageBody": "",
            "insertions": 8,
            "deletions": 7
          },
          {
            "hash": "e02e0886cf2995ecc2fc0eb40b51d7edb966270c",
            "messageTitle": "fixed test issues",
            "messageBody": "",
            "insertions": 7,
            "deletions": 3
          }
        ]
      },
      {
        "insertions": 1104,
        "deletions": 230,
        "date": "2020-03-26",
        "commitResults": [
          {
            "hash": "48a0dd9bf239a86de9342b062785cced5ab1b115",
            "messageTitle": "separate views for rooms/guets",
            "messageBody": "",
            "insertions": 23,
            "deletions": 4
          },
          {
            "hash": "d6a4d8298a6ba05ce3ea575ff74e7d1bb4233025",
            "messageTitle": "fix merge conflicts",
            "messageBody": "",
            "insertions": 4,
            "deletions": 4
          },
          {
            "hash": "1c6180efae74f9a200deeefe45440927ed57ad7e",
            "messageTitle": "fixed travis errors",
            "messageBody": "",
            "insertions": 23,
            "deletions": 26
          },
          {
            "hash": "d96b717ac75263ef81d555d22c0d670ac1a0a904",
            "messageTitle": "connected view room list into switch tabs to alternate between lists",
            "messageBody": "",
            "insertions": 38,
            "deletions": 3
          },
          {
            "hash": "537820bbaa15fe8e1ca91461c50e129697beabaf",
            "messageTitle": "reverted commit",
            "messageBody": "",
            "insertions": 801,
            "deletions": 123
          },
          {
            "hash": "8724447db6419abf08e70a6685e5661d536d480b",
            "messageTitle": "minor Ui issue",
            "messageBody": "",
            "insertions": 0,
            "deletions": 7
          },
          {
            "hash": "40888c98c167c4057459d436103e39212518f2e8",
            "messageTitle": "test issue",
            "messageBody": "",
            "insertions": 2,
            "deletions": 2
          },
          {
            "hash": "e542629916e6f9b79a881cf3d0d641504d657d02",
            "messageTitle": "test issues",
            "messageBody": "",
            "insertions": 0,
            "deletions": 2
          },
          {
            "hash": "da5b3d12ed57fe35ca346bcd8f62214c1615abf8",
            "messageTitle": "fixed bugs regarding saving hotel to external storage",
            "messageBody": "",
            "insertions": 213,
            "deletions": 59
          }
        ]
      },
      {
        "insertions": 108,
        "deletions": 261,
        "date": "2020-03-28",
        "commitResults": [
          {
            "hash": "4a5526ddf5595899a449734047b0d87500dab488",
            "messageTitle": "added requested changes",
            "messageBody": "",
            "insertions": 108,
            "deletions": 162
          },
          {
            "hash": "3cc6edfae47eeebe8e791cfb14e7991c444d6bf4",
            "messageTitle": "shifted tests to other branch",
            "messageBody": "",
            "insertions": 0,
            "deletions": 99
          }
        ]
      },
      {
        "insertions": 4,
        "deletions": 12,
        "date": "2020-03-29",
        "commitResults": [
          {
            "hash": "435100629955f91276618c4f058d1036d37e97b8",
            "messageTitle": "applied requested changes",
            "messageBody": "",
            "insertions": 4,
            "deletions": 12
          }
        ]
      },
      {
        "insertions": 518,
        "deletions": 133,
        "date": "2020-03-31",
        "commitResults": [
          {
            "hash": "9d95c2ca76fefa0c14d707a491204f36f24cad3d",
            "messageTitle": "tied storage to booking list",
            "messageBody": "",
            "insertions": 157,
            "deletions": 8
          },
          {
            "hash": "998e607c12114d141b8b3bb652cdda930615de4e",
            "messageTitle": "minor fix",
            "messageBody": "",
            "insertions": 1,
            "deletions": 1
          },
          {
            "hash": "8ed5e958d9b56b634e84991cafefef85d2cd7109",
            "messageTitle": "more minor javadoc fixes",
            "messageBody": "",
            "insertions": 92,
            "deletions": 2
          },
          {
            "hash": "8fe54d20b4b4dfed7b0ca5d0833a8a905c6098f2",
            "messageTitle": "fixed duplicate file",
            "messageBody": "",
            "insertions": 0,
            "deletions": 90
          },
          {
            "hash": "afc9f4efe8514ce41804f619ab9b2c89efdd3fbb",
            "messageTitle": "view bookings on the ui",
            "messageBody": "",
            "insertions": 221,
            "deletions": 19
          },
          {
            "hash": "56b4107c4dc4713239138fb255bd99bb1bcce8c4",
            "messageTitle": "fixed bugs",
            "messageBody": "",
            "insertions": 41,
            "deletions": 10
          },
          {
            "hash": "11cc3d3e3d8e6632626182e6f6e694d3d4435c9e",
            "messageTitle": "applied changes",
            "messageBody": "",
            "insertions": 2,
            "deletions": 1
          },
          {
            "hash": "910b23dd103831a7aad38be8d39e10758e6229cd",
            "messageTitle": "added requested changes",
            "messageBody": "",
            "insertions": 2,
            "deletions": 0
          },
          {
            "hash": "b5999c2c9f340deb666267a3f3ff0b641b88759b",
            "messageTitle": "added requested changes",
            "messageBody": "",
            "insertions": 1,
            "deletions": 1
          },
          {
            "hash": "51557373ee89156afa85f5548cef2346f11a230d",
            "messageTitle": "fixed whitespace error",
            "messageBody": "",
            "insertions": 1,
            "deletions": 1
          }
        ]
      },
      {
        "insertions": 157,
        "deletions": 42,
        "date": "2020-04-06",
        "commitResults": [
          {
            "hash": "f2d6d7998fac4aee079a3fddee42bebd0ea9d389",
            "messageTitle": "changed Ui",
            "messageBody": "",
            "insertions": 31,
            "deletions": 12
          },
          {
            "hash": "bdf57defac7fc1a81cb7d6d00b7a4a203b9518f4",
            "messageTitle": "changing Ui",
            "messageBody": "",
            "insertions": 66,
            "deletions": 4
          },
          {
            "hash": "7daafd782796f1fffb7ca69c0f05d118c567f02d",
            "messageTitle": "changing Ui",
            "messageBody": "",
            "insertions": 45,
            "deletions": 25
          },
          {
            "hash": "4598dc137680000623e206f883e5fb8f4f2bdbb2",
            "messageTitle": "fix CI errors",
            "messageBody": "",
            "insertions": 15,
            "deletions": 1
          }
        ]
      },
      {
        "insertions": 293,
        "deletions": 142,
        "date": "2020-04-10",
        "commitResults": [
          {
            "hash": "0ad1da9b075fed68153991bc38c56083930fa004",
            "messageTitle": "fixed booking Ui issue",
            "messageBody": "",
            "insertions": 156,
            "deletions": 5
          },
          {
            "hash": "254b225960dd323cd18b5b2fccb0cd2f5d6f05a1",
            "messageTitle": "staylist Ui",
            "messageBody": "",
            "insertions": 65,
            "deletions": 0
          },
          {
            "hash": "38d158012dd301f733717bd66c82b01786e1f9ff",
            "messageTitle": "fixed reserve bug",
            "messageBody": "",
            "insertions": 3,
            "deletions": 64
          },
          {
            "hash": "74b3bb3e4a3b68e6484e18e960a67d176ee938f4",
            "messageTitle": "fixed CI",
            "messageBody": "",
            "insertions": 0,
            "deletions": 3
          },
          {
            "hash": "8c9745b9244b9d14a6fffd2977d9ef79b61dbfcb",
            "messageTitle": "Added Ui for stay list",
            "messageBody": "",
            "insertions": 32,
            "deletions": 11
          },
          {
            "hash": "8f5f8fc6b9f45c4d08b01465c3e58b4364a530ac",
            "messageTitle": "fixed some issues",
            "messageBody": "",
            "insertions": 31,
            "deletions": 55
          },
          {
            "hash": "68abb8eda32b7ec7f01b11abfc7bd13ee612ee21",
            "messageTitle": "applied some requested changes",
            "messageBody": "",
            "insertions": 6,
            "deletions": 4
          }
        ]
      },
      {
        "insertions": 112,
        "deletions": 53,
        "date": "2020-04-11",
        "commitResults": [
          {
            "hash": "f8e97d05d8e9ad6f49032dd3d22f067d53772190",
            "messageTitle": "merge conflicts",
            "messageBody": "",
            "insertions": 1,
            "deletions": 0
          },
          {
            "hash": "c301b78d9c39e28db4a790247c10ff5708ac8efd",
            "messageTitle": "Applied requested changes",
            "messageBody": "",
            "insertions": 6,
            "deletions": 13
          },
          {
            "hash": "6931ef87b1902e699b0e019492a48232ce254005",
            "messageTitle": "remove debug messages",
            "messageBody": "",
            "insertions": 0,
            "deletions": 1
          },
          {
            "hash": "60f80cccaba0bcc635df1bdcd4e0499a71bf9189",
            "messageTitle": "Revert \"4Revert \"Added Ui for Stay\"\"",
            "messageBody": "",
            "insertions": 105,
            "deletions": 30
          },
          {
            "hash": "4ebb8f2ba3cb25bc6c5c7ffc407165740d1bc480",
            "messageTitle": "resolved some issues regarding ui for stay",
            "messageBody": "",
            "insertions": 0,
            "deletions": 9
          }
        ]
      },
      {
        "insertions": 8,
        "deletions": 8,
        "date": "2020-04-12",
        "commitResults": [
          {
            "hash": "26734038f7be5bf51ded53df5e49d6eea53464b2",
            "messageTitle": "Tag values reflect guest status",
            "messageBody": "",
            "insertions": 8,
            "deletions": 8
          }
        ]
      }
    ],
    "tanphatls987": [
      {
        "insertions": 178,
        "deletions": 104,
        "date": "2020-03-07",
        "commitResults": [
          {
            "hash": "1b9b933aa21c66418c70af596b0eadfd017cabd2",
            "messageTitle": "Change package person to hotel and add skeleton code",
            "messageBody": "",
            "insertions": 178,
            "deletions": 104
          }
        ]
      },
      {
        "insertions": 329,
        "deletions": 42,
        "date": "2020-03-10",
        "commitResults": [
          {
            "hash": "dd8c89a072bdd4521ed54595f6ef8d5d0ae7ff2e",
            "messageTitle": "Write AddGuestCommand skeleton",
            "messageBody": "",
            "insertions": 94,
            "deletions": 0
          },
          {
            "hash": "c95ae1f8fcf2cc206fd031d692bdec3ccaff18cd",
            "messageTitle": "Write Add Guest command",
            "messageBody": "",
            "insertions": 235,
            "deletions": 42
          }
        ]
      },
      {
        "insertions": 363,
        "deletions": 568,
        "date": "2020-03-12",
        "commitResults": [
          {
            "hash": "9b54e8315a25cc9ae00e9b664d8c922f42a324e7",
            "messageTitle": "Modified things related to personId",
            "messageBody": "",
            "insertions": 359,
            "deletions": 377
          },
          {
            "hash": "fb6e40b54fe74244ce4ef4947ad72cfae8cba880",
            "messageTitle": "Reverse experimental changes",
            "messageBody": "",
            "insertions": 4,
            "deletions": 191
          }
        ]
      },
      {
        "insertions": 784,
        "deletions": 182,
        "date": "2020-03-17",
        "commitResults": [
          {
            "hash": "4a317f26d99c5727830e1392f6bde3f82b043cc6",
            "messageTitle": "Remodified reserveCommand + add UI for personId",
            "messageBody": "",
            "insertions": 392,
            "deletions": 91
          },
          {
            "hash": "035834b3a425faa42450f37ae48b063971574850",
            "messageTitle": "Remodified reserveCommand + add UI for personId",
            "messageBody": "",
            "insertions": 392,
            "deletions": 91
          }
        ]
      },
      {
        "insertions": 485,
        "deletions": 325,
        "date": "2020-03-19",
        "commitResults": [
          {
            "hash": "26cbd4c8880dbbd5d4bb4e7a1d5fc0279ea3e520",
            "messageTitle": "Modified search command",
            "messageBody": "",
            "insertions": 357,
            "deletions": 263
          },
          {
            "hash": "e0da37df4dd477f69504f4cef2794f8b1532ce1a",
            "messageTitle": "Modify find guest command",
            "messageBody": "",
            "insertions": 128,
            "deletions": 62
          }
        ]
      },
      {
        "insertions": 108,
        "deletions": 28,
        "date": "2020-03-25",
        "commitResults": [
          {
            "hash": "90b7f368562c2dfcb73bf74e9fa28bb9c923871b",
            "messageTitle": "Add tab to switch between view",
            "messageBody": "",
            "insertions": 104,
            "deletions": 22
          },
          {
            "hash": "02043c8a87a9da446fd156fe132ca50634096151",
            "messageTitle": "Minor checkstyle error",
            "messageBody": "",
            "insertions": 4,
            "deletions": 6
          }
        ]
      },
      {
        "insertions": 43,
        "deletions": 1,
        "date": "2020-04-04",
        "commitResults": [
          {
            "hash": "14fd009d2b160bd229330240d2282c2999d71968",
            "messageTitle": "Disable adding person with same personId",
            "messageBody": "",
            "insertions": 43,
            "deletions": 1
          }
        ]
      },
      {
        "insertions": 608,
        "deletions": 86,
        "date": "2020-04-05",
        "commitResults": [
          {
            "hash": "cf2e547403508f91f5e01ba049b712dcf0278653",
            "messageTitle": "Change roomcost and related function",
            "messageBody": "",
            "insertions": 12,
            "deletions": 0
          },
          {
            "hash": "19fe1414d88f3b60ef22ce8fe3e81f95916c3fdb",
            "messageTitle": "Fix regex expression for cost, fix setroomcost.",
            "messageBody": "",
            "insertions": 286,
            "deletions": 41
          },
          {
            "hash": "0d67b067f2fc825c013120de3a8009cfb88163ed",
            "messageTitle": "Change roomcost and related function",
            "messageBody": "",
            "insertions": 12,
            "deletions": 0
          },
          {
            "hash": "17af7d04c62634462d1ce7300c128a9da752d4ed",
            "messageTitle": "Fix regex expression for cost, fix setroomcost.",
            "messageBody": "",
            "insertions": 287,
            "deletions": 43
          },
          {
            "hash": "308bc9591e23f0eb0ee619e34c6c12ece8c9876e",
            "messageTitle": "Fix merge conflict",
            "messageBody": "",
            "insertions": 11,
            "deletions": 2
          }
        ]
      },
      {
        "insertions": 403,
        "deletions": 12,
        "date": "2020-04-10",
        "commitResults": [
          {
            "hash": "0bf33e39ea263325c64acf83f44058289679d510",
            "messageTitle": "Add command to switch between tabs.",
            "messageBody": "",
            "insertions": 306,
            "deletions": 6
          },
          {
            "hash": "dd28fc361d04fd5a9b1bae24b73524d29a0fa98e",
            "messageTitle": "Conflict resolved",
            "messageBody": "",
            "insertions": 0,
            "deletions": 6
          },
          {
            "hash": "71df87277e519ac2fefe16bcd4a183b040d713c9",
            "messageTitle": "Add command to find empty room from start date to end date",
            "messageBody": "",
            "insertions": 97,
            "deletions": 0
          }
        ]
      },
      {
        "insertions": 9,
        "deletions": 3,
        "date": "2020-04-11",
        "commitResults": [
          {
            "hash": "c10efe4d3663e46380df62437c7a79fd927ddcf3",
            "messageTitle": "Change in UG and switch view command",
            "messageBody": "",
            "insertions": 6,
            "deletions": 3
          },
          {
            "hash": "09412c4c9e9176d12f502e09cdc1cc7a1d109065",
            "messageTitle": "Add Portpolio and small update to guide",
            "messageBody": "",
            "insertions": 3,
            "deletions": 0
          }
        ]
      }
    ],
    "dawidjaja": [
      {
        "insertions": 12,
        "deletions": 11,
        "date": "2020-03-11",
        "commitResults": [
          {
            "hash": "57d7233403b2562e7e4730fbd6c991d58468f239",
            "messageTitle": "add CheckInCommand",
            "messageBody": "",
            "insertions": 12,
            "deletions": 11
          }
        ]
      },
      {
        "insertions": 236,
        "deletions": 77,
        "date": "2020-03-17",
        "commitResults": [
          {
            "hash": "3b285e54124142955b50deddacb6e2f78cc8cf3d",
            "messageTitle": "add checkin parser",
            "messageBody": "",
            "insertions": 107,
            "deletions": 2
          },
          {
            "hash": "4220a1058ed6ef58a0a895a4dd449c47eb9bf630",
            "messageTitle": "add checkin command",
            "messageBody": "",
            "insertions": 54,
            "deletions": 21
          },
          {
            "hash": "561cd5b18a91d9d257fc8b8325c978d5e8d1aa3a",
            "messageTitle": "add todate",
            "messageBody": "",
            "insertions": 14,
            "deletions": 10
          },
          {
            "hash": "2ff7a86923228e71b153b0aa17447a31909fe748",
            "messageTitle": "add command result",
            "messageBody": "",
            "insertions": 1,
            "deletions": 1
          },
          {
            "hash": "0739d84c0ad04c00b2fcf28be446c95445525806",
            "messageTitle": "add documentation",
            "messageBody": "",
            "insertions": 9,
            "deletions": 0
          },
          {
            "hash": "397f7892bd503ddc8c4f2a15639226f5fa9e9607",
            "messageTitle": "fix import order",
            "messageBody": "",
            "insertions": 8,
            "deletions": 8
          },
          {
            "hash": "bf4a1892e91e3490bfb23a8fe105a8b9a05253d5",
            "messageTitle": "remove duplicate import",
            "messageBody": "",
            "insertions": 0,
            "deletions": 1
          },
          {
            "hash": "b6e213f0a75166cf2e928298b3946496029ece66",
            "messageTitle": "change to localDateTime",
            "messageBody": "",
            "insertions": 43,
            "deletions": 33
          },
          {
            "hash": "71859c786b3187e984d74f0c7174dc011d5129d5",
            "messageTitle": "remove unused import",
            "messageBody": "",
            "insertions": 0,
            "deletions": 1
          }
        ]
      },
      {
        "insertions": 17,
        "deletions": 16,
        "date": "2020-03-20",
        "commitResults": [
          {
            "hash": "00c09000ce8d3af84c048f976c01b3c03daad8ea",
            "messageTitle": "Update MatchNamePredicateTest.java",
            "messageBody": "",
            "insertions": 5,
            "deletions": 4
          },
          {
            "hash": "c4f4b01c92269aa80afb83d7ff943ef9553ab21e",
            "messageTitle": "Update MatchPersonIdPredicateTest.java",
            "messageBody": "",
            "insertions": 4,
            "deletions": 3
          },
          {
            "hash": "67960f8b893ba167afc450bd0dd1d6154437bbc4",
            "messageTitle": "Update MatchPersonIdPredicateTest.java",
            "messageBody": "",
            "insertions": 2,
            "deletions": 2
          },
          {
            "hash": "850eabbf01e6a9550dec1a85cbaaffd29be026ec",
            "messageTitle": "Update MatchNamePredicateTest.java",
            "messageBody": "",
            "insertions": 2,
            "deletions": 2
          },
          {
            "hash": "782d9bac2f1a645362dd4311ce30bdc4117842cd",
            "messageTitle": "Update MatchNamePredicateTest.java",
            "messageBody": "",
            "insertions": 2,
            "deletions": 3
          },
          {
            "hash": "b8d6c063588494c3c4b302096a330f9477f2e78f",
            "messageTitle": "Update MatchPersonIdPredicateTest.java",
            "messageBody": "",
            "insertions": 2,
            "deletions": 2
          }
        ]
      },
      {
        "insertions": 366,
        "deletions": 10,
        "date": "2020-03-24",
        "commitResults": [
          {
            "hash": "fbee2fd8ae9e10b3d0286ab1c25c37248478010b",
            "messageTitle": "add test",
            "messageBody": "",
            "insertions": 339,
            "deletions": 1
          },
          {
            "hash": "2399d0fb4ad60170e9ae3b800b4a9f105bbdf1dc",
            "messageTitle": "move roomList to Hotel.java",
            "messageBody": "",
            "insertions": 15,
            "deletions": 4
          },
          {
            "hash": "e2c0f2008987e0303eb774f6b574d5b0f944c24c",
            "messageTitle": "fix travis",
            "messageBody": "",
            "insertions": 11,
            "deletions": 4
          },
          {
            "hash": "c851d39e257b12cf9f2ac0069a23b4a932ee96ce",
            "messageTitle": "hook travis",
            "messageBody": "",
            "insertions": 1,
            "deletions": 1
          }
        ]
      },
      {
        "insertions": 60,
        "deletions": 37,
        "date": "2020-03-28",
        "commitResults": [
          {
            "hash": "fe95139988f9224c3701b30d24e2da1099376586",
            "messageTitle": "fix clash check",
            "messageBody": "",
            "insertions": 39,
            "deletions": 6
          },
          {
            "hash": "76c83b4fd8593d7e341052c0bdf6ac292f81a99a",
            "messageTitle": "fix stub",
            "messageBody": "",
            "insertions": 6,
            "deletions": 12
          },
          {
            "hash": "3b9bd6d949da8b589843647494364bba8cf0bada",
            "messageTitle": "fix stub",
            "messageBody": "",
            "insertions": 0,
            "deletions": 9
          },
          {
            "hash": "7f39e839f10bb7d45d446e849170dbfc327c61bb",
            "messageTitle": "fix test",
            "messageBody": "",
            "insertions": 13,
            "deletions": 9
          },
          {
            "hash": "b18bfab14d042e1b0735fe73beeaf77c136e93b7",
            "messageTitle": "fix travis",
            "messageBody": "",
            "insertions": 2,
            "deletions": 1
          }
        ]
      },
      {
        "insertions": 7,
        "deletions": 3,
        "date": "2020-03-29",
        "commitResults": [
          {
            "hash": "13f0ab7358137eddba8de4020ea51a36d8449ae9",
            "messageTitle": "Update ModelManager.java",
            "messageBody": "",
            "insertions": 7,
            "deletions": 3
          }
        ]
      },
      {
        "insertions": 10,
        "deletions": 18,
        "date": "2020-03-30",
        "commitResults": [
          {
            "hash": "2424db5fd98550c38d21d1451dcc76070c7da080",
            "messageTitle": "change datetime parse format",
            "messageBody": "",
            "insertions": 3,
            "deletions": 2
          },
          {
            "hash": "63d227a1f83dc0f6ffe008fe5f40deb407a99a84",
            "messageTitle": "fix merge",
            "messageBody": "",
            "insertions": 0,
            "deletions": 4
          },
          {
            "hash": "50e8aaea49b06f43f1ba92a348c7665af3ca54e5",
            "messageTitle": "fix travis",
            "messageBody": "",
            "insertions": 5,
            "deletions": 10
          },
          {
            "hash": "e4cc2fbd6abca545e441fc00d4ebe51e579c3c38",
            "messageTitle": "fix",
            "messageBody": "",
            "insertions": 2,
            "deletions": 2
          }
        ]
      },
      {
        "insertions": 287,
        "deletions": 56,
        "date": "2020-03-31",
        "commitResults": [
          {
            "hash": "dbffab58e17628a5c0cd0a6cc1dbc64ef66ed112",
            "messageTitle": "add checkout command",
            "messageBody": "",
            "insertions": 137,
            "deletions": 21
          },
          {
            "hash": "8707613ec488a4c20ce5e2ca19d92edcdd2201e7",
            "messageTitle": "add checkout command",
            "messageBody": "",
            "insertions": 98,
            "deletions": 21
          },
          {
            "hash": "4e7b7ba58eb9caaf94971c3f3ff835896c995853",
            "messageTitle": "fix checkin test",
            "messageBody": "",
            "insertions": 50,
            "deletions": 13
          },
          {
            "hash": "939751fe9e520830fde8ccc1e722c8c7454b5871",
            "messageTitle": "add checker script",
            "messageBody": "",
            "insertions": 1,
            "deletions": 0
          },
          {
            "hash": "8f1f278b98aa7be963098081e15101dd262f4c94",
            "messageTitle": "Update CheckInCommandTest.java",
            "messageBody": "",
            "insertions": 1,
            "deletions": 1
          }
        ]
      },
      {
        "insertions": 33,
        "deletions": 23,
        "date": "2020-04-01",
        "commitResults": [
          {
            "hash": "88117ffcf7df5bcfaca5f1f1296a4d54e9f5e73a",
            "messageTitle": "fix",
            "messageBody": "",
            "insertions": 7,
            "deletions": 7
          },
          {
            "hash": "0c160dce250c2b9f2d009ffa3aa526db3d565966",
            "messageTitle": "init tier",
            "messageBody": "",
            "insertions": 3,
            "deletions": 0
          },
          {
            "hash": "83db91727889a6331fbb696909f1d5cbc3e7231e",
            "messageTitle": "fix jar build",
            "messageBody": "",
            "insertions": 9,
            "deletions": 8
          },
          {
            "hash": "6790bf20deadac751f7cb506497179fb1e1463aa",
            "messageTitle": "fix travis",
            "messageBody": "",
            "insertions": 12,
            "deletions": 6
          },
          {
            "hash": "6d7994407dd93ed00f8d99614007c4040543b7ae",
            "messageTitle": "fix test",
            "messageBody": "",
            "insertions": 1,
            "deletions": 1
          },
          {
            "hash": "dff69b8c80d7c6f83e9ba721f5aea7667468dc7f",
            "messageTitle": "id to lowercase",
            "messageBody": "",
            "insertions": 1,
            "deletions": 1
          }
        ]
      },
      {
        "insertions": 68,
        "deletions": 18,
        "date": "2020-04-03",
        "commitResults": [
          {
            "hash": "4ec355be34f786aa9e5f77be2a1857f84ec18cf0",
            "messageTitle": "make label lowercase",
            "messageBody": "",
            "insertions": 9,
            "deletions": 9
          },
          {
            "hash": "3d27ba27fe8e05caec6067aaab69ad1f2a38628f",
            "messageTitle": "make lowercase",
            "messageBody": "",
            "insertions": 2,
            "deletions": 2
          },
          {
            "hash": "436dcf9b3817634b6a6895118b85016e36c8a9f8",
            "messageTitle": "add null handler",
            "messageBody": "",
            "insertions": 3,
            "deletions": 0
          },
          {
            "hash": "adf7f378756da9f89c87d81fa6d50c73474238f6",
            "messageTitle": "add tier and cost to addroom",
            "messageBody": "",
            "insertions": 47,
            "deletions": 6
          },
          {
            "hash": "eb036840b1ec7e0a6f5c8b70ac3ade64b09d524e",
            "messageTitle": "add user guide",
            "messageBody": "",
            "insertions": 7,
            "deletions": 1
          }
        ]
      },
      {
        "insertions": 72,
        "deletions": 36,
        "date": "2020-04-07",
        "commitResults": [
          {
            "hash": "955824dab13c1ce14ef284172552202818cfb022",
            "messageTitle": "Update src/main/java/seedu/address/model/Hotel.java",
            "messageBody": "",
            "insertions": 1,
            "deletions": 1
          },
          {
            "hash": "a28df1aecfdc956e5ddb11e34c406facc09b3e40",
            "messageTitle": "Update src/main/java/seedu/address/model/Hotel.java",
            "messageBody": "",
            "insertions": 0,
            "deletions": 1
          },
          {
            "hash": "713f1e239010ced5515f170364c50f17cf0918d1",
            "messageTitle": "fix conflict",
            "messageBody": "",
            "insertions": 0,
            "deletions": 4
          },
          {
            "hash": "18d337259b0dad0d949b5d2271d4e30c3b51f9c2",
            "messageTitle": "fix add room",
            "messageBody": "",
            "insertions": 36,
            "deletions": 13
          },
          {
            "hash": "71e28e0c1513227a9c97a9f56c21244a6633b2e8",
            "messageTitle": "fix travis",
            "messageBody": "",
            "insertions": 35,
            "deletions": 17
          }
        ]
      },
      {
        "insertions": 210,
        "deletions": 82,
        "date": "2020-04-08",
        "commitResults": [
          {
            "hash": "ffc0d4cb087f237e6fdd7e45ad8acc2dc69fa9bf",
            "messageTitle": "add stay list",
            "messageBody": "",
            "insertions": 135,
            "deletions": 42
          },
          {
            "hash": "d712660cb91a52b7ad256683f27321fd9c17a0f4",
            "messageTitle": "move to another branch",
            "messageBody": "",
            "insertions": 1,
            "deletions": 2
          },
          {
            "hash": "9b6bbc77fd780b06de2a5869f6b06eb5b289516f",
            "messageTitle": "fix travis",
            "messageBody": "",
            "insertions": 74,
            "deletions": 38
          }
        ]
      },
      {
        "insertions": 1,
        "deletions": 0,
        "date": "2020-04-09",
        "commitResults": [
          {
            "hash": "6025f15f4800713171e0e5e687086d12321390bb",
            "messageTitle": "hot fix add bill",
            "messageBody": "",
            "insertions": 1,
            "deletions": 0
          }
        ]
      },
      {
        "insertions": 130,
        "deletions": 13,
        "date": "2020-04-10",
        "commitResults": [
          {
            "hash": "c872e7838dbe254ff7c12a4456780b9e44b4d91b",
            "messageTitle": "checkin check from stay list instead of booking list",
            "messageBody": "",
            "insertions": 1,
            "deletions": 1
          },
          {
            "hash": "e45b6d5fd114bcaba6b8741c1755642bac42f81a",
            "messageTitle": "add booking ID",
            "messageBody": "",
            "insertions": 125,
            "deletions": 9
          },
          {
            "hash": "a2778693aa9a3929729d9a6b432aba84e80a3685",
            "messageTitle": "check if the room number is the same during checkin",
            "messageBody": "",
            "insertions": 2,
            "deletions": 1
          },
          {
            "hash": "e49eeb45ba268d6d714ee276422e1d02332c4d15",
            "messageTitle": "fix travis",
            "messageBody": "",
            "insertions": 2,
            "deletions": 2
          }
        ]
      },
      {
        "insertions": 83,
        "deletions": 113,
        "date": "2020-04-11",
        "commitResults": [
          {
            "hash": "063f1fea1046b676350b5c867a545abc120dae31",
            "messageTitle": "add expired and too early exception",
            "messageBody": "",
            "insertions": 14,
            "deletions": 0
          },
          {
            "hash": "08ac1a184823194fc6e70774bc6a5bf57481bfdc",
            "messageTitle": "fix travis",
            "messageBody": "",
            "insertions": 39,
            "deletions": 8
          },
          {
            "hash": "6eb551b20d31a227a809e9436e5038ef42b74f27",
            "messageTitle": "Revert \"Added Ui for Stay\"",
            "messageBody": "",
            "insertions": 30,
            "deletions": 105
          }
        ]
      },
      {
        "insertions": 385,
        "deletions": 53,
        "date": "2020-04-12",
        "commitResults": [
          {
            "hash": "9fa5ee0f1c4dda72b1e4f94c2f12e50d3adc720e",
            "messageTitle": "add extend command",
            "messageBody": "",
            "insertions": 252,
            "deletions": 4
          },
          {
            "hash": "02100b1e6670d41a1e1d095b172e5aa9c9e6a6c9",
            "messageTitle": "reset json adapter booking",
            "messageBody": "",
            "insertions": 3,
            "deletions": 12
          },
          {
            "hash": "59b98bf3b22f67f3103379a8d39bc2ed8a3b8264",
            "messageTitle": "fix hotel load from json",
            "messageBody": "",
            "insertions": 40,
            "deletions": 11
          },
          {
            "hash": "818e506293135acfc8ce904fb152eb68dc7b72d2",
            "messageTitle": "fix travis",
            "messageBody": "",
            "insertions": 2,
            "deletions": 3
          },
          {
            "hash": "2fb0630ea7d15a2ab6ef88260064542bc5185e59",
            "messageTitle": "fix travis\u0027",
            "messageBody": "",
            "insertions": 69,
            "deletions": 18
          },
          {
            "hash": "40434c8fe6c89963c9a5d62d86d2e77eb1256eab",
            "messageTitle": "add date format exception",
            "messageBody": "",
            "insertions": 11,
            "deletions": 1
          },
          {
            "hash": "3c14a316759049721462286bf8ddcec207b03169",
            "messageTitle": "fix travis",
            "messageBody": "",
            "insertions": 0,
            "deletions": 1
          },
          {
            "hash": "b82131d255cda702e953e6af96a875c135925324",
            "messageTitle": "fix site name and github link",
            "messageBody": "",
            "insertions": 2,
            "deletions": 2
          },
          {
            "hash": "763afb65fb6ceffbf66df1cc5eee182c7a35e41c",
            "messageTitle": "add javadoc",
            "messageBody": "",
            "insertions": 6,
            "deletions": 1
          }
        ]
      }
    ],
    "youaremysky99": [
      {
        "insertions": 82,
        "deletions": 0,
        "date": "2020-03-07",
        "commitResults": [
          {
            "hash": "a1a44375d29134e57766169ead595f539ff64fc0",
            "messageTitle": "add-skeleton-codes",
            "messageBody": "",
            "insertions": 82,
            "deletions": 0
          }
        ]
      },
      {
        "insertions": 125,
        "deletions": 31,
        "date": "2020-03-10",
        "commitResults": [
          {
            "hash": "438514876922b06b092ae5ab7f1fe142268cfe80",
            "messageTitle": "add-skeleton-codes",
            "messageBody": "",
            "insertions": 10,
            "deletions": 3
          },
          {
            "hash": "5f7c9d61f7d6dacc37570ef90b1cccfa6f67f483",
            "messageTitle": "add-skeleton-codes",
            "messageBody": "",
            "insertions": 82,
            "deletions": 1
          },
          {
            "hash": "b317c7ed242fdbdde31cb38e319f6814f875cd13",
            "messageTitle": "checkstyle",
            "messageBody": "",
            "insertions": 33,
            "deletions": 27
          }
        ]
      },
      {
        "insertions": 257,
        "deletions": 4,
        "date": "2020-03-17",
        "commitResults": [
          {
            "hash": "5fb7e0fa7511b975270bbc01f65c07113bd39062",
            "messageTitle": "addHotel",
            "messageBody": "",
            "insertions": 103,
            "deletions": 3
          },
          {
            "hash": "11c21ea9f9dcbcd4c6dfd29960b6b486d8eed4ef",
            "messageTitle": "addHotel",
            "messageBody": "",
            "insertions": 4,
            "deletions": 0
          },
          {
            "hash": "9fbc0979f4dc201ef94545682b6bfca4f44d172d",
            "messageTitle": "addCommand-and-Parser",
            "messageBody": "",
            "insertions": 101,
            "deletions": 1
          },
          {
            "hash": "b239aab62c77c471415823ee777a354b9e9b800c",
            "messageTitle": "addTest",
            "messageBody": "",
            "insertions": 49,
            "deletions": 0
          }
        ]
      },
      {
        "insertions": 186,
        "deletions": 10,
        "date": "2020-03-18",
        "commitResults": [
          {
            "hash": "47d20aab36b858e353458faa8c52dd084d00c601",
            "messageTitle": "addTestForHotel",
            "messageBody": "",
            "insertions": 123,
            "deletions": 9
          },
          {
            "hash": "7021df4a0a567e9aa5a69f113291ba60aa2c2aea",
            "messageTitle": "addEvenMoreTests",
            "messageBody": "",
            "insertions": 63,
            "deletions": 1
          }
        ]
      },
      {
        "insertions": 538,
        "deletions": 35,
        "date": "2020-03-24",
        "commitResults": [
          {
            "hash": "b00d8f448de8147d3532449988cd0100cb935a12",
            "messageTitle": "addTests",
            "messageBody": "",
            "insertions": 29,
            "deletions": 1
          },
          {
            "hash": "d79fea6fc5c8ca9924dec09dc7f996bf8f2ed2c4",
            "messageTitle": "addCommand-and-Parser",
            "messageBody": "",
            "insertions": 191,
            "deletions": 8
          },
          {
            "hash": "8c080de5b6f42844102737f402660650ee7e71c1",
            "messageTitle": "addParserTests",
            "messageBody": "",
            "insertions": 142,
            "deletions": 1
          },
          {
            "hash": "9d0ae370b9c48cf14cc3e560c45be6fd291dc746",
            "messageTitle": "addParserTests",
            "messageBody": "",
            "insertions": 8,
            "deletions": 0
          },
          {
            "hash": "4b912c596a2806a4c480e9db1ff0748baf808854",
            "messageTitle": "addIntegrationTest",
            "messageBody": "",
            "insertions": 167,
            "deletions": 21
          },
          {
            "hash": "15834067a52709ccbedd88f81599acf8bb10bd7b",
            "messageTitle": "fixCheckstyle",
            "messageBody": "",
            "insertions": 1,
            "deletions": 4
          }
        ]
      },
      {
        "insertions": 4,
        "deletions": 21,
        "date": "2020-03-25",
        "commitResults": [
          {
            "hash": "1a17be9b563d910be8095fb4ad8da292dda1b130",
            "messageTitle": "fixCheckstyle",
            "messageBody": "",
            "insertions": 4,
            "deletions": 21
          }
        ]
      },
      {
        "insertions": 255,
        "deletions": 11,
        "date": "2020-04-05",
        "commitResults": [
          {
            "hash": "29a4b04a80a3bb1950bd4a36cb6714b9617dc2a2",
            "messageTitle": "addAvailableServices",
            "messageBody": "",
            "insertions": 70,
            "deletions": 0
          },
          {
            "hash": "97b5d26b4512dd343570980b7789cb9b94ef69e1",
            "messageTitle": "addServiceCommand",
            "messageBody": "",
            "insertions": 172,
            "deletions": 7
          },
          {
            "hash": "7fb5396e281f2c6882538e3457c33dbf30d34ea3",
            "messageTitle": "minorFix",
            "messageBody": "",
            "insertions": 1,
            "deletions": 1
          },
          {
            "hash": "bbe3b492f410f874b55a13f344061f783d682df7",
            "messageTitle": "minorFix",
            "messageBody": "",
            "insertions": 3,
            "deletions": 2
          },
          {
            "hash": "a0be2985dab27eabac5dfa3c2a918c1e7463c723",
            "messageTitle": "fixCheckstyle",
            "messageBody": "",
            "insertions": 3,
            "deletions": 1
          },
          {
            "hash": "2e48bb688e4dc1d2514daa39ce86ba84eb9b9a25",
            "messageTitle": "fixConfliting",
            "messageBody": "",
            "insertions": 6,
            "deletions": 0
          }
        ]
      },
      {
        "insertions": 196,
        "deletions": 4,
        "date": "2020-04-06",
        "commitResults": [
          {
            "hash": "cbd6391c7fd9fb4d65a66dbd8afb3579887eeb43",
            "messageTitle": "addSeviceCommandTest",
            "messageBody": "",
            "insertions": 35,
            "deletions": 0
          },
          {
            "hash": "e5207b816e288ce72373e0e4aa112290789a6f65",
            "messageTitle": "addSeviceCommandIntegrationTest",
            "messageBody": "",
            "insertions": 65,
            "deletions": 1
          },
          {
            "hash": "b68f25b725a06a3fd392ef314cd52d0f9dbd3e39",
            "messageTitle": "addJsonAvailableService",
            "messageBody": "",
            "insertions": 75,
            "deletions": 0
          },
          {
            "hash": "77f6e89e8e2ceb6d900283a7044afbecd543522c",
            "messageTitle": "addStorage",
            "messageBody": "",
            "insertions": 21,
            "deletions": 3
          }
        ]
      },
      {
        "insertions": 562,
        "deletions": 5,
        "date": "2020-04-07",
        "commitResults": [
          {
            "hash": "589311c2f39d43179b1b2f65c4d26f1fd593acad",
            "messageTitle": "addUiFiles",
            "messageBody": "",
            "insertions": 153,
            "deletions": 0
          },
          {
            "hash": "e94cc9b1f9f50fd5eb0793abaad3043303bc241c",
            "messageTitle": "addUiFiles",
            "messageBody": "",
            "insertions": 18,
            "deletions": 0
          },
          {
            "hash": "a6ea4d98a318e2dce4237ce0ded8dd6b033f286b",
            "messageTitle": "addCommand-and-Parser",
            "messageBody": "",
            "insertions": 145,
            "deletions": 0
          },
          {
            "hash": "9040fdb2de26db1180ab214f1b9a2aea4996217d",
            "messageTitle": "checkStyle",
            "messageBody": "",
            "insertions": 0,
            "deletions": 3
          },
          {
            "hash": "32263137c4eae7c7070d9048712068f80f6ddfae",
            "messageTitle": "addCommand-and-Parser",
            "messageBody": "",
            "insertions": 4,
            "deletions": 0
          },
          {
            "hash": "1797017bfc017d3f76f99cef73db98677da63a4b",
            "messageTitle": "add-DeleteRoomCommandTest",
            "messageBody": "",
            "insertions": 45,
            "deletions": 0
          },
          {
            "hash": "7f53616732bbe7d876e8c1c1f9a3663b867055e5",
            "messageTitle": "add-DeleteRoomCommandIntegrationTest",
            "messageBody": "",
            "insertions": 46,
            "deletions": 0
          },
          {
            "hash": "9789ff32df92ed46fdd62a22ac34d79fb527552c",
            "messageTitle": "add",
            "messageBody": "",
            "insertions": 12,
            "deletions": 0
          },
          {
            "hash": "d6eedc2ecdab50909dba17a5aed1f99c4b39e24b",
            "messageTitle": "addParser",
            "messageBody": "",
            "insertions": 139,
            "deletions": 2
          }
        ]
      },
      {
        "insertions": 394,
        "deletions": 28,
        "date": "2020-04-08",
        "commitResults": [
          {
            "hash": "1f6e032f7fb2d5cd5d91aaab48e150bf68d7424f",
            "messageTitle": "addTests",
            "messageBody": "",
            "insertions": 59,
            "deletions": 0
          },
          {
            "hash": "59237ceea2ba7c147c7c37f0134d32ce327a7571",
            "messageTitle": "addIntegrationTest",
            "messageBody": "",
            "insertions": 61,
            "deletions": 1
          },
          {
            "hash": "7919d26f9f7ced17792996f9c6f8ea59172c37db",
            "messageTitle": "addFindBookingCommand",
            "messageBody": "",
            "insertions": 8,
            "deletions": 0
          },
          {
            "hash": "3cd7e6f4dea4249d98c51f9fad065f3f7ef6eaae",
            "messageTitle": "addFindBookingCommand",
            "messageBody": "",
            "insertions": 128,
            "deletions": 2
          },
          {
            "hash": "1a2115749b073d7cf508d1faad3aa8eaf664fb4d",
            "messageTitle": "refactorSomePredicates",
            "messageBody": "",
            "insertions": 138,
            "deletions": 25
          }
        ]
      },
      {
        "insertions": 416,
        "deletions": 11,
        "date": "2020-04-09",
        "commitResults": [
          {
            "hash": "e4877a224c52c61ad3b3c8cf67a5eeb63fc04eab",
            "messageTitle": "finishFindBookingCommand",
            "messageBody": "",
            "insertions": 72,
            "deletions": 2
          },
          {
            "hash": "5166b8eab6a49b56a2753e2129128857b647f63a",
            "messageTitle": "finishFindBookingCommandParser",
            "messageBody": "",
            "insertions": 82,
            "deletions": 0
          },
          {
            "hash": "60ee5481f1ceaef9078b7e7dee85c5e345b84aa3",
            "messageTitle": "finishEditingAddressbookParser",
            "messageBody": "",
            "insertions": 4,
            "deletions": 0
          },
          {
            "hash": "fb7dc84d80a329362e70f6261d924e91543ad9c5",
            "messageTitle": "fixUI",
            "messageBody": "",
            "insertions": 12,
            "deletions": 2
          },
          {
            "hash": "8a0fda5d51faa8c116072508fe25d44d976baa35",
            "messageTitle": "smallFix",
            "messageBody": "",
            "insertions": 1,
            "deletions": 1
          },
          {
            "hash": "58d9dbd5702e7e37882c2df088b5fbec56f7416b",
            "messageTitle": "smallFix",
            "messageBody": "",
            "insertions": 0,
            "deletions": 1
          },
          {
            "hash": "a63c92033fa60c7c2e03a5868c228b053e2dfab2",
            "messageTitle": "add-FindRoomCommand",
            "messageBody": "",
            "insertions": 159,
            "deletions": 0
          },
          {
            "hash": "8ff4d31a6201d2e2f25545f733614314297db0c1",
            "messageTitle": "minorFix",
            "messageBody": "",
            "insertions": 1,
            "deletions": 1
          },
          {
            "hash": "9d523b22bb3d787c2ee4d80bf52533c6888a2cd2",
            "messageTitle": "add-FindRoomCommandParser",
            "messageBody": "",
            "insertions": 79,
            "deletions": 2
          },
          {
            "hash": "6d61e97d511443e981de635ced8c60dd5d7f24be",
            "messageTitle": "add-FindRoomCommandParser",
            "messageBody": "",
            "insertions": 5,
            "deletions": 1
          },
          {
            "hash": "33755bc4bf9ae169a37ba4161118c5bdf0781d62",
            "messageTitle": "add-FindRoomCommandParser",
            "messageBody": "",
            "insertions": 1,
            "deletions": 1
          }
        ]
      },
      {
        "insertions": 84,
        "deletions": 7,
        "date": "2020-04-10",
        "commitResults": [
          {
            "hash": "cf285365d6f905e569ba4541fc67f47f2d7cfa39",
            "messageTitle": "integrateFilteredRoomList",
            "messageBody": "",
            "insertions": 18,
            "deletions": 0
          },
          {
            "hash": "0324a324251c8c68a71f30bad192c74a3e4b8a88",
            "messageTitle": "minorFix",
            "messageBody": "",
            "insertions": 1,
            "deletions": 1
          },
          {
            "hash": "81bcf9b2ae2ebbfe0a637c794b2a992f72ab6aae",
            "messageTitle": "add-StayJson",
            "messageBody": "",
            "insertions": 52,
            "deletions": 5
          },
          {
            "hash": "ad00030474dd684f81c8a91538f6fd304eb43ccc",
            "messageTitle": "change-JsonHotel",
            "messageBody": "",
            "insertions": 13,
            "deletions": 1
          }
        ]
      },
      {
        "insertions": 307,
        "deletions": 29,
        "date": "2020-04-11",
        "commitResults": [
          {
            "hash": "40cec7569d59be0a77a43194c5b7c6e2e1baf27a",
            "messageTitle": "changeSomeBehaviors",
            "messageBody": "",
            "insertions": 15,
            "deletions": 8
          },
          {
            "hash": "cf6374e2a635694685662a9665428d84e9d86edf",
            "messageTitle": "changeAddRoomResponse",
            "messageBody": "",
            "insertions": 6,
            "deletions": 0
          },
          {
            "hash": "293a05c19d02ac1334231f5db88f2d36c966122d",
            "messageTitle": "minorFix",
            "messageBody": "",
            "insertions": 3,
            "deletions": 1
          },
          {
            "hash": "3775ec46a33befa9b79e846424fcab47c842fd03",
            "messageTitle": "addServiceResponse",
            "messageBody": "",
            "insertions": 16,
            "deletions": 15
          },
          {
            "hash": "eae0bc1966b704f80b759c3ed0c69ae23b0483b4",
            "messageTitle": "fixst",
            "messageBody": "",
            "insertions": 2,
            "deletions": 0
          },
          {
            "hash": "e83579fdc2bd16d1cee94a821be5416b6b27409b",
            "messageTitle": "add",
            "messageBody": "",
            "insertions": 8,
            "deletions": 3
          },
          {
            "hash": "73538d000e6b08e44896f158bb54e0dbc9cef662",
            "messageTitle": "add",
            "messageBody": "",
            "insertions": 11,
            "deletions": 1
          },
          {
            "hash": "9088cfa627f5ac9e184eb8ae6b4c00df350d3f19",
            "messageTitle": "add",
            "messageBody": "",
            "insertions": 1,
            "deletions": 1
          },
          {
            "hash": "be00981c4b7886c4a4c9681cf4ace90c7fb2ed63",
            "messageTitle": "add",
            "messageBody": "",
            "insertions": 245,
            "deletions": 0
          }
        ]
      },
      {
        "insertions": 268,
        "deletions": 82,
        "date": "2020-04-12",
        "commitResults": [
          {
            "hash": "ac9ae764aae556557457c7ae33ac25a42d154f1d",
            "messageTitle": "addParser",
            "messageBody": "",
            "insertions": 74,
            "deletions": 3
          },
          {
            "hash": "6fc2d297d88bd6ee24a96c482421f6f2d52ebb51",
            "messageTitle": "add",
            "messageBody": "",
            "insertions": 4,
            "deletions": 0
          },
          {
            "hash": "949ab6d9d19ce424a249ac7e85f3ac6e4e639caa",
            "messageTitle": "addParser",
            "messageBody": "",
            "insertions": 70,
            "deletions": 25
          },
          {
            "hash": "e0aa57ea81492196d5623b4f55f72c84d0f0abc1",
            "messageTitle": "addParser",
            "messageBody": "",
            "insertions": 51,
            "deletions": 22
          },
          {
            "hash": "a5e4a01bb316338c1fe141394c072db53aa4a085",
            "messageTitle": "fixUsage",
            "messageBody": "",
            "insertions": 5,
            "deletions": 2
          },
          {
            "hash": "2201dfd4c2121ee823644b249c139b5ed361b181",
            "messageTitle": "updateParser",
            "messageBody": "",
            "insertions": 63,
            "deletions": 29
          },
          {
            "hash": "bb3b7c8a04ddad66d6c7535ff48f1dbad87bbd76",
            "messageTitle": "fixBug",
            "messageBody": "",
            "insertions": 1,
            "deletions": 1
          }
        ]
      }
    ],
    "hmtey": [
      {
        "insertions": 48,
        "deletions": 0,
        "date": "2020-03-15",
        "commitResults": [
          {
            "hash": "82e1790535ac47ee32cb97b96abcc566a080b577",
            "messageTitle": "Added FetchBillCommand and FetchBillCommandParser classes",
            "messageBody": "",
            "insertions": 48,
            "deletions": 0
          }
        ]
      },
      {
        "insertions": 21,
        "deletions": 6,
        "date": "2020-03-17",
        "commitResults": [
          {
            "hash": "9cd26c4a71e338cf158384a9e62259ab622f740d",
            "messageTitle": "Updated skeleton for FetchBillCommand",
            "messageBody": "",
            "insertions": 12,
            "deletions": 2
          },
          {
            "hash": "0f89b82676794e0e5d60f57562fb36906aded9e6",
            "messageTitle": "Fixed checkstyle errors",
            "messageBody": "",
            "insertions": 9,
            "deletions": 4
          }
        ]
      },
      {
        "insertions": 256,
        "deletions": 86,
        "date": "2020-03-18",
        "commitResults": [
          {
            "hash": "223d690614bbce9324add2fad8ddd2c2ad010f68",
            "messageTitle": "Updated FetchBillCommand \u0026 FetchBillCommandParser",
            "messageBody": "",
            "insertions": 60,
            "deletions": 16
          },
          {
            "hash": "0b4265924b162ffe7de1438e12300ade37ba1663",
            "messageTitle": "Updated FetchBillCommand \u0026 FetchBillCommandParser",
            "messageBody": "",
            "insertions": 62,
            "deletions": 13
          },
          {
            "hash": "2cb88a34db76c1b66a0e9030819141d145c496db",
            "messageTitle": "Added basic functionality to FetchBillCommand",
            "messageBody": "",
            "insertions": 32,
            "deletions": 10
          },
          {
            "hash": "3f699e34e8a52710a46238e7c671e8d277d986a9",
            "messageTitle": "Fixed wrong message showing.",
            "messageBody": "",
            "insertions": 1,
            "deletions": 2
          },
          {
            "hash": "6c32167e8264aade67700b151f5cd3cd1bb1fe23",
            "messageTitle": "Added FetchBillCommandParserTest",
            "messageBody": "",
            "insertions": 58,
            "deletions": 0
          },
          {
            "hash": "f063080baa5b59b4b4d8ee96e4bd7cd9fdd5db85",
            "messageTitle": "Fixed bugs in FetchBill",
            "messageBody": "",
            "insertions": 10,
            "deletions": 13
          },
          {
            "hash": "4cf90805eb9be2a54ecc69ec5c6ba2d6915a9090",
            "messageTitle": "Fixed checkstyle errors",
            "messageBody": "",
            "insertions": 0,
            "deletions": 5
          },
          {
            "hash": "d0d72480fb641aaf28ec09587a4a089e0a178a01",
            "messageTitle": "Fixed bugs",
            "messageBody": "",
            "insertions": 4,
            "deletions": 4
          },
          {
            "hash": "b6273995b1e66abbbcf171fc6545f125b40345e8",
            "messageTitle": "Fixed checkstyle errors",
            "messageBody": "",
            "insertions": 2,
            "deletions": 8
          },
          {
            "hash": "3a5a97db08ba7bbbb862a5f205cc0bc88cec3ba2",
            "messageTitle": "Updated test",
            "messageBody": "",
            "insertions": 10,
            "deletions": 0
          },
          {
            "hash": "18d65d6d1c4cf863f8bd7d7391651488860ee59a",
            "messageTitle": "Fixed merge conflict",
            "messageBody": "",
            "insertions": 2,
            "deletions": 1
          },
          {
            "hash": "aeeb228d0544cadf684ddc4feb2f2d196eaf8f88",
            "messageTitle": "Fixed checkstyle errors",
            "messageBody": "",
            "insertions": 1,
            "deletions": 1
          },
          {
            "hash": "d846447ab5cccc0cddb781c4256d58091fbc0af4",
            "messageTitle": "Updated FetchBillCommandParserTest",
            "messageBody": "",
            "insertions": 6,
            "deletions": 6
          },
          {
            "hash": "3ccbfd6f0a365a0deadc4859d160af9e4bc675ce",
            "messageTitle": "Fixed checkstyle error",
            "messageBody": "",
            "insertions": 2,
            "deletions": 1
          },
          {
            "hash": "75723d68447bb63da95cac25f6f43312a1f2d0a7",
            "messageTitle": "Updated FetchFillCommandParserTest",
            "messageBody": "",
            "insertions": 2,
            "deletions": 2
          },
          {
            "hash": "f88ad5f7e18b78067f603f4a90fb05d836ecc82d",
            "messageTitle": "Fixed checkstyle errors",
            "messageBody": "",
            "insertions": 4,
            "deletions": 4
          }
        ]
      },
      {
        "insertions": 2,
        "deletions": 7,
        "date": "2020-03-20",
        "commitResults": [
          {
            "hash": "a78010948b5cf36bacc05d1c3675bde42cbbdc33",
            "messageTitle": "Applied requested changes",
            "messageBody": "",
            "insertions": 2,
            "deletions": 7
          }
        ]
      },
      {
        "insertions": 294,
        "deletions": 148,
        "date": "2020-03-24",
        "commitResults": [
          {
            "hash": "be61a50c4ca8ad0a9672c6f4add55d8b3b551449",
            "messageTitle": "Updated FetchBillCommand \u0026 FetchBillCommandParser",
            "messageBody": "",
            "insertions": 60,
            "deletions": 16
          },
          {
            "hash": "f44a7890f5101b4fd57e1d7155b971a32002138f",
            "messageTitle": "Updated FetchBillCommand \u0026 FetchBillCommandParser",
            "messageBody": "",
            "insertions": 63,
            "deletions": 32
          },
          {
            "hash": "dfc21a088aa19c2d2fb550c2ec582956d12cf092",
            "messageTitle": "Added basic functionality to FetchBillCommand",
            "messageBody": "",
            "insertions": 35,
            "deletions": 43
          },
          {
            "hash": "2cad857bd647bf67c6441f75ae1b77cbcc5765a4",
            "messageTitle": "Fixed wrong message showing.",
            "messageBody": "",
            "insertions": 1,
            "deletions": 2
          },
          {
            "hash": "20a23e80e3b0a14449a420efb822524cf2e8d68c",
            "messageTitle": "Added FetchBillCommandParserTest",
            "messageBody": "",
            "insertions": 58,
            "deletions": 0
          },
          {
            "hash": "ac8b86ada1c0498056ac82e9661c90eac85f61fb",
            "messageTitle": "Fixed bugs in FetchBill",
            "messageBody": "",
            "insertions": 10,
            "deletions": 13
          },
          {
            "hash": "56b6e0d83fac79a656794b5a9e671d9e604b6398",
            "messageTitle": "Fixed checkstyle errors",
            "messageBody": "",
            "insertions": 0,
            "deletions": 5
          },
          {
            "hash": "48ea7086114c75279e62a180d1581ba1f9f22c14",
            "messageTitle": "Fixed bugs",
            "messageBody": "",
            "insertions": 4,
            "deletions": 4
          },
          {
            "hash": "e5ad44193555f65eae8b48ea50b3a306c2ae57c8",
            "messageTitle": "Fixed checkstyle errors",
            "messageBody": "",
            "insertions": 2,
            "deletions": 8
          },
          {
            "hash": "93b16a28f3a662580f1fcfe67811fd2bf3d65682",
            "messageTitle": "Updated test",
            "messageBody": "",
            "insertions": 10,
            "deletions": 0
          },
          {
            "hash": "ab8b8a7ef3eb1b1a99ca0a2d8817550eed978440",
            "messageTitle": "Fixed merge conflict",
            "messageBody": "",
            "insertions": 34,
            "deletions": 4
          },
          {
            "hash": "3cc2ce5610073b84c178524af597892655cc9e59",
            "messageTitle": "Fixed checkstyle errors",
            "messageBody": "",
            "insertions": 1,
            "deletions": 1
          },
          {
            "hash": "3fa1a4ca4a9d778ac9ef15d8761bd1229aa443ec",
            "messageTitle": "Updated FetchBillCommandParserTest",
            "messageBody": "",
            "insertions": 6,
            "deletions": 6
          },
          {
            "hash": "d27faee33b24a2ed083dd332f2baa9067347f600",
            "messageTitle": "Fixed checkstyle error",
            "messageBody": "",
            "insertions": 2,
            "deletions": 1
          },
          {
            "hash": "dac47a44daa519fec4d005f3588b8f80699bbb7a",
            "messageTitle": "Updated FetchFillCommandParserTest",
            "messageBody": "",
            "insertions": 2,
            "deletions": 2
          },
          {
            "hash": "714da3918ae77a6a786dad4f71a9ec2a739056fa",
            "messageTitle": "Fixed checkstyle errors",
            "messageBody": "",
            "insertions": 4,
            "deletions": 4
          },
          {
            "hash": "756a7ebf8367a22487089ecea8652045861e80aa",
            "messageTitle": "Applied requested changes",
            "messageBody": "",
            "insertions": 2,
            "deletions": 7
          }
        ]
      },
      {
        "insertions": 354,
        "deletions": 96,
        "date": "2020-03-25",
        "commitResults": [
          {
            "hash": "ff345643f80b4f6c768f15adf01c6f8a8602f2d6",
            "messageTitle": "Fleshed out Bill, Chargeable, RoomCost \u0026 Service classes",
            "messageBody": "",
            "insertions": 88,
            "deletions": 22
          },
          {
            "hash": "c2510de025b36a9d61fc6e0b2070c81b41b15b7f",
            "messageTitle": "Packaged classes related to billing system",
            "messageBody": "",
            "insertions": 4,
            "deletions": 4
          },
          {
            "hash": "c8a8b48bd655c02d73d0c43cf4665c9f9a7917b1",
            "messageTitle": "Extracted Cost class from Service \u0026 RoomCost.",
            "messageBody": "",
            "insertions": 54,
            "deletions": 42
          },
          {
            "hash": "fb02ee72d75300b89b3ee35d185f3db49516d482",
            "messageTitle": "Added Set Room Cost Command",
            "messageBody": "",
            "insertions": 193,
            "deletions": 26
          },
          {
            "hash": "d4860e25890cc42c92ad931711f76824c64fc96a",
            "messageTitle": "Fixed checkstyle errors",
            "messageBody": "",
            "insertions": 15,
            "deletions": 2
          }
        ]
      },
      {
        "insertions": 1,
        "deletions": 1,
        "date": "2020-03-31",
        "commitResults": [
          {
            "hash": "738cf27356a1b467b7d2f0d01e1bbd811fd1f1ec",
            "messageTitle": "Fixed checkstyle errors",
            "messageBody": "",
            "insertions": 1,
            "deletions": 1
          }
        ]
      },
      {
        "insertions": 204,
        "deletions": 10,
        "date": "2020-04-03",
        "commitResults": [
          {
            "hash": "0256afd4b3bcf4afc06d33de90efe1c234ecc6ad",
            "messageTitle": "Fixed checkstyle",
            "messageBody": "",
            "insertions": 1,
            "deletions": 1
          },
          {
            "hash": "e4751831da53cc25f11e64e337eddea3009957b8",
            "messageTitle": "Added Service Command + Fixed cost bug",
            "messageBody": "",
            "insertions": 185,
            "deletions": 7
          },
          {
            "hash": "6e891c40626ce33f041f750de3a898baaff5db66",
            "messageTitle": "Fixed checkstyle errors",
            "messageBody": "",
            "insertions": 18,
            "deletions": 2
          }
        ]
      },
      {
        "insertions": 10,
        "deletions": 9,
        "date": "2020-04-04",
        "commitResults": [
          {
            "hash": "7836d087826ae57160da52fe551f7e0377f753c3",
            "messageTitle": "Fixed PE-D issues (Addressbook ref \u0026 UG update)",
            "messageBody": "",
            "insertions": 8,
            "deletions": 7
          },
          {
            "hash": "183539fefb0aafd52294a524ac7ff21536e47eac",
            "messageTitle": "Fixed errors",
            "messageBody": "",
            "insertions": 2,
            "deletions": 2
          }
        ]
      },
      {
        "insertions": 140,
        "deletions": 75,
        "date": "2020-04-05",
        "commitResults": [
          {
            "hash": "df5d983230e06526553a922eea73b13fe3292828",
            "messageTitle": "Fixed bugs",
            "messageBody": "",
            "insertions": 63,
            "deletions": 13
          },
          {
            "hash": "9dff266a61dedb863073079319fcf3f2004dcae4",
            "messageTitle": "Fixed checkstyle errors",
            "messageBody": "",
            "insertions": 13,
            "deletions": 3
          },
          {
            "hash": "22317d9c74afc202b06350445861f43d824b5d1e",
            "messageTitle": "Refactored code (ServiceCommand -\u003e ChargeServiceCommand)",
            "messageBody": "",
            "insertions": 11,
            "deletions": 11
          },
          {
            "hash": "8c8ded51b2d43c3e8363157b65edf053bc5712fa",
            "messageTitle": "Updated \u0026 standardized usage messages",
            "messageBody": "",
            "insertions": 36,
            "deletions": 33
          },
          {
            "hash": "00c818ac9e896ada4482c91b6bf8814ec79304c2",
            "messageTitle": "Updated feedback messages",
            "messageBody": "",
            "insertions": 10,
            "deletions": 8
          },
          {
            "hash": "61222320380fdbfdf8765533867f5b8fae6a32d1",
            "messageTitle": "Fixed bug",
            "messageBody": "",
            "insertions": 3,
            "deletions": 3
          },
          {
            "hash": "203f3efb07682bd63c4b899ce01f8ff5e593128d",
            "messageTitle": "Fixed checkstyle error",
            "messageBody": "",
            "insertions": 1,
            "deletions": 1
          },
          {
            "hash": "50b401c5124fbf9a0f50dcbfb11f6ff0be201252",
            "messageTitle": "Updated feedback messages",
            "messageBody": "",
            "insertions": 3,
            "deletions": 3
          }
        ]
      },
      {
        "insertions": 343,
        "deletions": 169,
        "date": "2020-04-07",
        "commitResults": [
          {
            "hash": "b6fbee95a2c258f174bbda8ab783e1995ed73714",
            "messageTitle": "Updated chargeservice command",
            "messageBody": "",
            "insertions": 329,
            "deletions": 79
          },
          {
            "hash": "fd8b30e3a125b920b8b864509d4ff6643711cc5c",
            "messageTitle": "Removed Service class",
            "messageBody": "",
            "insertions": 0,
            "deletions": 64
          },
          {
            "hash": "09a6db53b9bd3921d4a66e2d130293717645ccac",
            "messageTitle": "Fixed checkstyle",
            "messageBody": "",
            "insertions": 0,
            "deletions": 13
          },
          {
            "hash": "4051fe004f0bc06caffa235d87c254f63cc15887",
            "messageTitle": "Updated chargeservice command",
            "messageBody": "",
            "insertions": 14,
            "deletions": 13
          }
        ]
      },
      {
        "insertions": 84,
        "deletions": 20,
        "date": "2020-04-09",
        "commitResults": [
          {
            "hash": "926eb91404ca23b92a37dd7942eb9fe1866e3954",
            "messageTitle": "Undo changes to hotel.json",
            "messageBody": "",
            "insertions": 84,
            "deletions": 20
          }
        ]
      },
      {
        "insertions": 1162,
        "deletions": 220,
        "date": "2020-04-10",
        "commitResults": [
          {
            "hash": "3e561540088acb052f3010b5455736e4d98fd4ed",
            "messageTitle": "Fixed errors from merge conflict",
            "messageBody": "",
            "insertions": 0,
            "deletions": 11
          },
          {
            "hash": "1933803b1c45705c99f27bd802a13de1b1ab90c5",
            "messageTitle": "Added Bill Tab",
            "messageBody": "",
            "insertions": 212,
            "deletions": 22
          },
          {
            "hash": "02286491c520f91a0d0b73722ed9c9261f2484bd",
            "messageTitle": "Fixed errors",
            "messageBody": "",
            "insertions": 55,
            "deletions": 16
          },
          {
            "hash": "8ab441d1b9733b2c2417e2db482c3d0fca0c4625",
            "messageTitle": "Added storage for bills.",
            "messageBody": "",
            "insertions": 160,
            "deletions": 18
          },
          {
            "hash": "95c10d8c5093c6ae0d6d0938a01ba0f2b1527c9a",
            "messageTitle": "Added BookKeeper class to manage bills",
            "messageBody": "",
            "insertions": 735,
            "deletions": 153
          }
        ]
      },
      {
        "insertions": 348,
        "deletions": 147,
        "date": "2020-04-11",
        "commitResults": [
          {
            "hash": "4614ca87b56a2527aa23f1f0f53f90e77c1433fc",
            "messageTitle": "Fixed bugs",
            "messageBody": "",
            "insertions": 109,
            "deletions": 48
          },
          {
            "hash": "edd2f2f4a6fbc3c038190022a5f10e3f661833cc",
            "messageTitle": "Fixed checkstyle",
            "messageBody": "",
            "insertions": 158,
            "deletions": 73
          },
          {
            "hash": "98d6b43f6499da87aeb4242525aa35587c0f2e53",
            "messageTitle": "Updated Sample Data",
            "messageBody": "",
            "insertions": 5,
            "deletions": 1
          },
          {
            "hash": "41f80da752551e0a7188a121c91fb275c574662b",
            "messageTitle": "Fixed checkstyle",
            "messageBody": "",
            "insertions": 0,
            "deletions": 1
          },
          {
            "hash": "de06d65ad6fd495b11371f58dc6c6e5283abb77c",
            "messageTitle": "Updated charging of roomcost",
            "messageBody": "",
            "insertions": 76,
            "deletions": 24
          }
        ]
      },
      {
        "insertions": 259,
        "deletions": 13,
        "date": "2020-04-12",
        "commitResults": [
          {
            "hash": "3ad08da07eedea84665fdef62ec480d538eef112",
            "messageTitle": "Added DeleteChargedService command",
            "messageBody": "",
            "insertions": 246,
            "deletions": 5
          },
          {
            "hash": "58b101f285b947f2d3fb583b01e8f6df12591fe9",
            "messageTitle": "Fixed roomcost calculation bug",
            "messageBody": "",
            "insertions": 8,
            "deletions": 1
          },
          {
            "hash": "7761a038c0ad3462c08a6413f40439ae411b204f",
            "messageTitle": "Fixed merge conflicts",
            "messageBody": "",
            "insertions": 5,
            "deletions": 7
          }
        ]
      }
    ]
  },
  "authorFinalContributionMap": {
    "sancharib-git": 2344,
    "tanphatls987": 1909,
    "dawidjaja": 1632,
    "youaremysky99": 3168,
    "hmtey": 2612
  },
  "authorFileTypeContributionMap": {
    "sancharib-git": {
      "docs": 0,
      "functional-code": 1863,
      "test-code": 481
    },
    "tanphatls987": {
      "docs": 0,
      "functional-code": 1213,
      "test-code": 696
    },
    "dawidjaja": {
      "docs": 0,
      "functional-code": 1129,
      "test-code": 500,
      "other": 3
    },
    "youaremysky99": {
      "docs": 0,
      "functional-code": 2459,
      "test-code": 708,
      "other": 1
    },
    "hmtey": {
      "docs": 0,
      "functional-code": 2295,
      "test-code": 317
    }
  },
  "authorContributionVariance": {
    "sancharib-git": 68267.97,
    "tanphatls987": 50498.305,
    "dawidjaja": 10465.548,
    "youaremysky99": 20985.916,
    "hmtey": 46846.586
  },
  "authorDisplayNameMap": {
    "sancharib-git": "CS2103T-W13-2 SANC..HYAY",
    "tanphatls987": "CS2103T-W13-2 TRAN..PHAT",
    "dawidjaja": "CS2103T-W13-2 DANI..JAJA",
    "youaremysky99": "CS2103T-W13-2 LE Q..TUAN",
    "hmtey": "CS2103T-W13-2 TEY ..MING"
  }
}
